Workbook

Sheet Cover
B2: EMEA Banking Sector - NIM Sensitivity Model
B4: Author: Samrudhi Shevare
B5: Coverage: Barclays, BNP Paribas, Deutsche Bank
B6: Source: Company annual reports, Yahoo Finance (yfinance)
B8: Contents | C8: Description
B9: Model Sheets
B10: =HYPERLINK("#Assumptions!A1","Assumptions") -> Assumptions | C10: Scenario toggle, central bank rates, bank-level inputs (β, lag, tax)
B11: =HYPERLINK("#Calc_Barclays!A1","Calc_Barclays") -> Calc_Barclays | C11: Barclays FY24A vs FY25E P&L and ratios (£bn)
B12: =HYPERLINK("#Calc_BNP!A1","Calc_BNP") -> Calc_BNP | C12: BNP Paribas FY24A vs FY25E P&L and ratios (€bn)
B13: =HYPERLINK("#Calc_Deutsche!A1","Calc_Deutsche") -> Calc_Deutsche | C13: Deutsche Bank FY24A vs FY25E P&L and ratios (€bn)
B14: =HYPERLINK("#Sensitivity!A1","Sensitivity") -> Sensitivity | C14: ROE grids: ΔRate × deposit β for all three banks, with heatmap
B15: =HYPERLINK("#Scenarios!A1","Scenarios") -> Scenarios | C15: Bear / Base / Bull FY25E outputs side by side
B16: =HYPERLINK("#Chartbook!A1","Chartbook") -> Chartbook | C16: Four charts: Net Income by scenario, historical ROE/NIM, FY24 C/I
B18: Source Data
B19: =HYPERLINK("#ratios_summary!A1","ratios_summary") -> ratios_summary | C19: Historical NIM / ROE / ROA / C/I / Net Income by bank & year
B20: =HYPERLINK("#sensitivity_results!A1","sensitivity_results") -> sensitivity_results | C20: Prior Python sensitivity output (reference)
B21: =HYPERLINK("#income_Barclays!A1","income_Barclays") -> income_Barclays | C21: Barclays income statement FY2021 - FY2025 (raw £)
B22: =HYPERLINK("#income_BNP_Paribas!A1","income_BNP_Paribas") -> income_BNP_Paribas | C22: BNP Paribas income statement FY2021 - FY2025 (raw €)
B23: =HYPERLINK("#income_Deutsche_Bank!A1","income_Deutsche_Bank") -> income_Deutsche_Bank | C23: Deutsche Bank income statement FY2022 - FY2025 (raw €)
B24: =HYPERLINK("#balance_Barclays!A1","balance_Barclays") -> balance_Barclays | C24: Barclays balance sheet FY2022 - FY2025 (raw £)
B25: =HYPERLINK("#balance_BNP_Paribas!A1","balance_BNP_Paribas") -> balance_BNP_Paribas | C25: BNP Paribas balance sheet FY2021 - FY2025 (raw €)
B26: =HYPERLINK("#balance_Deutsche_Bank!A1","balance_Deutsche_Bank") -> balance_Deutsche_Bank | C26: Deutsche Bank balance sheet FY2022 - FY2025 (raw €)
B27: =HYPERLINK("#bank_metrics!A1","bank_metrics") -> bank_metrics | C27: Current price, market cap, P/B, P/E, ROE/ROA snapshot
B28: =HYPERLINK("#bank_prices!A1","bank_prices") -> bank_prices | C28: Daily share price history (Barclays, BNP, Deutsche)

Sheet Assumptions
A1: EMEA Banking NIM Model - Assumptions
A3: Scenario: | D3: Base | E3: ← change to Bear / Base / Bull
A5: Central Bank Rates | B5: Bear | C5: Base | D5: Bull | E5: Selected | F5: FY2024 Actual | G5: Δ Rate
A6: ECB Rate (eurozone) | B6: 0.0175 | C6: 0.0225 | D6: 0.0275 | E6: =CHOOSE(MATCH($D$3,{"Bear","Base","Bull"},0),B6,C6,D6) -> 0.0225 | F6: 0.0315 | G6: =E6-F6 -> -0.009
A7: BoE Rate (UK) | B7: 0.0375 | C7: 0.0425 | D7: 0.0475 | E7: =CHOOSE(MATCH($D$3,{"Bear","Base","Bull"},0),B7,C7,D7) -> 0.0425 | F7: 0.05 | G7: =E7-F7 -> -0.0075
A9: Bank Inputs | B9: Barclays | C9: BNP Paribas | D9: Deutsche Bank | E9: Central Bank
A10: Deposit Beta | B10: 0.42 | C10: 0.38 | D10: 0.32
A11: Repricing Lag | B11: 0.65 | C11: 0.6 | D11: 0.7
A12: Cost Inflation | B12: 0.02 | C12: 0.02 | D12: 0.02
A13: Fee Growth | B13: 0.02 | C13: 0.02 | D13: 0.02
A14: Tax Rate | B14: 0.22 | C14: 0.265 | D14: 0.25
A15: Applicable Rate Ref | B15: BoE | C15: ECB | D15: ECB
A17: Color key: | B17: Hardcoded input | C17: Formula | D17: Cross-sheet link | E17: Key toggle

Sheet Calc_Barclays
A1: Calc_Barclays - NIM-driven P&L (£bn)
A2: All figures in £ billions unless noted. Source figures divided by 1,000,000,000.
B4: FY2024A | C4: FY2025E
A6: Income Statement
A7: Net Interest Income | B7: =income_Barclays!C8/1000000000 -> 12.936 | C7: =C32*C35 -> 8.6432838
A8: Non-Interest Income (Fees) | B8: =B9-B7 -> 13.294 | C8: =B8*(1+Assumptions!B13) -> 13.55988
A9: Total Revenue | B9: =income_Barclays!C40/1000000000 -> 26.23 | C9: =C7+C8 -> 22.203164
A10: Operating Expense | B10: =income_Barclays!C32/1000000000 -> 15.964 | C10: =B10*(1+Assumptions!B12) -> 16.28328
A11: Pretax Income | B11: =income_Barclays!C26/1000000000 -> 8.108 | C11: =C9-C10 -> 5.9198838
A12: Tax Provision | B12: =income_Barclays!C25/1000000000 -> 1.752 | C12: =C11*Assumptions!B14 -> 1.3023744
A13: Net Income | B13: =income_Barclays!C20/1000000000 -> 6.307 | C13: =C11-C12 -> 4.6175094
A15: Balance Sheet
A16: Total Assets | B16: =balance_Barclays!C25/1000000000 -> 1518.202 | C16: =C35 -> 1518.202
A17: Common Stock Equity | B17: =balance_Barclays!C9/1000000000 -> 71.821 | C17: =B17+C13 -> 76.438509
A19: Key Ratios
A20: NIM (NII / Total Assets) | B20: =B7/B16 -> 0.0085206053 | C20: =C7/C16 -> 0.0056931053
A21: Effective Tax Rate | B21: =B12/B11 -> 0.21608288 | C21: =Assumptions!B14 -> 0.22
A22: ROE (Net Income / Equity) | B22: =B13/B17 -> 0.087815541 | C22: =C13/((B17+C17)/2) -> 0.062289555
A23: Cost-to-Income | B23: =B10/B9 -> 0.60861609 | C23: =C10/C9 -> 0.73337656
A25: FY25E Drivers
A26: Applicable CB rate (BoE) | C26: =Assumptions!E7 -> 0.0425
A27: FY24 CB rate | C27: =Assumptions!F7 -> 0.05
A28: Δ Rate | C28: =C26-C27 -> -0.0075
A29: Deposit Beta | C29: =Assumptions!B10 -> 0.42
A30: Repricing Lag | C30: =Assumptions!B11 -> 0.65
A31: NIM change = ΔRate × (1 − β) × Lag | C31: =C28*(1-C29)*C30 -> -0.0028275
A32: NIM FY25E | B32: =B20 -> 0.0085206053 | C32: =B20+C31 -> 0.0056931053
A34: FY25E P&L
A35: Total Assets (held flat) | C35: =B16 -> 1518.202

Sheet Calc_BNP
A1: Calc_BNP Paribas - NIM-driven P&L (€bn)
A2: All figures in € billions. Source figures divided by 1,000,000,000.
B4: FY2024A | C4: FY2025E
A6: Income Statement
A7: Net Interest Income | B7: =income_BNP_Paribas!C8/1000000000 -> 19.524 | C7: =C32*C35 -> 10.467968
A8: Non-Interest Income (Fees) | B8: =B9-B7 -> 46.346 | C8: =B8*(1+Assumptions!C13) -> 47.27292
A9: Total Revenue | B9: =income_BNP_Paribas!C41/1000000000 -> 65.87 | C9: =C7+C8 -> 57.740888
A10: Operating Expense | B10: =income_BNP_Paribas!C33/1000000000 -> 47.403 | C10: =B10*(1+Assumptions!C12) -> 48.35106
A11: Pretax Income | B11: =income_BNP_Paribas!C26/1000000000 -> 16.188 | C11: =C9-C10 -> 9.389828
A12: Tax Provision | B12: =income_BNP_Paribas!C25/1000000000 -> 4.001 | C12: =C11*Assumptions!C14 -> 2.4883044
A13: Net Income | B13: =income_BNP_Paribas!C20/1000000000 -> 11.688 | C13: =C11-C12 -> 6.9015236
A15: Balance Sheet
A16: Total Assets | B16: =balance_BNP_Paribas!C25/1000000000 -> 2704.908 | C16: =C35 -> 2704.908
A17: Common Stock Equity | B17: =balance_BNP_Paribas!C10/1000000000 -> 128.137 | C17: =B17+C13 -> 135.03852
A19: Key Ratios
A20: NIM (NII / Total Assets) | B20: =B7/B16 -> 0.0072179904 | C20: =C7/C16 -> 0.0038699904
A21: Effective Tax Rate | B21: =B12/B11 -> 0.24715839 | C21: =Assumptions!C14 -> 0.265
A22: ROE (Net Income / Equity) | B22: =B13/B17 -> 0.091214872 | C22: =C13/((B17+C17)/2) -> 0.052448066
A23: Cost-to-Income | B23: =B10/B9 -> 0.71964475 | C23: =C10/C9 -> 0.83737992
A25: FY25E Drivers
A26: Applicable CB rate (ECB) | C26: =Assumptions!E6 -> 0.0225
A27: FY24 CB rate | C27: =Assumptions!F6 -> 0.0315
A28: Δ Rate | C28: =C26-C27 -> -0.009
A29: Deposit Beta | C29: =Assumptions!C10 -> 0.38
A30: Repricing Lag | C30: =Assumptions!C11 -> 0.6
A31: NIM change = ΔRate × (1 − β) × Lag | C31: =C28*(1-C29)*C30 -> -0.003348
A32: NIM FY25E | B32: =B20 -> 0.0072179904 | C32: =B20+C31 -> 0.0038699904
A34: FY25E P&L
A35: Total Assets (held flat) | C35: =B16 -> 2704.908

Sheet Calc_Deutsche
A1: Calc_Deutsche Bank - NIM-driven P&L (€bn)
A2: All figures in € billions. OpEx = SG&A + Other Non Interest Expense. Source figures ÷ 1,000,000,000.
B4: FY2024A | C4: FY2025E
A6: Income Statement
A7: Net Interest Income | B7: =income_Deutsche_Bank!C7/1000000000 -> 13.064 | C7: =C32*C35 -> 7.1213337
A8: Non-Interest Income (Fees) | B8: =B9-B7 -> 16.983 | C8: =B8*(1+Assumptions!D13) -> 17.32266
A9: Total Revenue | B9: =income_Deutsche_Bank!C36/1000000000 -> 30.047 | C9: =C7+C8 -> 24.443994
A10: Operating Expense (SG&A + Other NIE) | B10: =(income_Deutsche_Bank!C31+income_Deutsche_Bank!C40)/1000000000 -> 18.02 | C10: =B10*(1+Assumptions!D12) -> 18.3804
A11: Pretax Income | B11: =income_Deutsche_Bank!C25/1000000000 -> 5.291 | C11: =C9-C10 -> 6.0635937
A12: Tax Provision (held at FY24 effective 33.8%) | B12: =income_Deutsche_Bank!C24/1000000000 -> 1.786 | C12: =C11*B21 -> 2.0467924
A13: Net Income | B13: =income_Deutsche_Bank!C20/1000000000 -> 3.366 | C13: =C11-C12 -> 4.0168014
A15: Balance Sheet
A16: Total Assets | B16: =balance_Deutsche_Bank!C40/1000000000 -> 1387.177 | C16: =C35 -> 1387.177
A17: Common Stock Equity | B17: =balance_Deutsche_Bank!C10/1000000000 -> 77.826 | C17: =B17+C13 -> 81.842801
A19: Key Ratios
A20: NIM (NII / Total Assets) | B20: =B7/B16 -> 0.0094176879 | C20: =C7/C16 -> 0.0051336879
A21: Effective Tax Rate | B21: =B12/B11 -> 0.33755434 | C21: =B21 -> 0.33755434
A22: ROE (Net Income / Equity) | B22: =B13/B17 -> 0.043250328 | C22: =C13/((B17+C17)/2) -> 0.050314167
A23: Cost-to-Income | B23: =B10/B9 -> 0.59972709 | C23: =C10/C9 -> 0.75193932
A25: FY25E Drivers
A26: Applicable CB rate (ECB) | C26: =Assumptions!E6 -> 0.0225
A27: FY24 CB rate | C27: =Assumptions!F6 -> 0.0315
A28: Δ Rate | C28: =C26-C27 -> -0.009
A29: Deposit Beta | C29: =Assumptions!D10 -> 0.32
A30: Repricing Lag | C30: =Assumptions!D11 -> 0.7
A31: NIM change = ΔRate × (1 − β) × Lag | C31: =C28*(1-C29)*C30 -> -0.004284
A32: NIM FY25E | B32: =B20 -> 0.0094176879 | C32: =B20+C31 -> 0.0051336879
A34: FY25E P&L
A35: Total Assets (held flat) | C35: =B16 -> 1387.177

Sheet Sensitivity
A1: FY2025E ROE Sensitivity - Rate Change vs Deposit Beta
A2: Base = FY2024 actuals. NIM FY25E = NIM FY24 + ΔRate×(1−β)×Lag. Fees & OpEx held flat; tax per each bank's rule.
A4: Barclays (BoE, Lag 65%, Tax 22%)
A5: ΔRate \ β | B5: 0.2 | C5: 0.3 | D5: 0.4 | E5: 0.5 | F5: 0.6 | G5: 0.7 | H5: 0.8
A6: -0.005 | B6: =(((Calc_Barclays!$B$20+$A6*(1-B$5)*Assumptions!$B$11)*Calc_Barclays!$B$16+Calc_Barclays!$B$8*(1+Assumptions!$B$13)-Calc_Barclays!$B$10*(1+Assumptions!$B$12))*(1-Assumptions!$B$14))/(Calc_Barclays!$B$17+(((Calc_Barclays!$B$20+$A6*(1-B$5)*Assumptions!$B$11)*Calc_Barclays!$B$16+Calc_Barclays!$B$8*(1+Assumptions!$B$13)-Calc_Barclays!$B$10*(1+Assumptions!$B$12))*(1-Assumptions!$B$14))/2) -> 0.065804216 | C6: =(((Calc_Barclays!$B$20+$A6*(1-C$5)*Assumptions!$B$11)*Calc_Barclays!$B$16+Calc_Barclays!$B$8*(1+Assumptions!$B$13)-Calc_Barclays!$B$10*(1+Assumptions!$B$12))*(1-Assumptions!$B$14))/(Calc_Barclays!$B$17+(((Calc_Barclays!$B$20+$A6*(1-C$5)*Assumptions!$B$11)*Calc_Barclays!$B$16+Calc_Barclays!$B$8*(1+Assumptions!$B$13)-Calc_Barclays!$B$10*(1+Assumptions!$B$12))*(1-Assumptions!$B$14))/2) -> 0.0708031 | D6: =(((Calc_Barclays!$B$20+$A6*(1-D$5)*Assumptions!$B$11)*Calc_Barclays!$B$16+Calc_Barclays!$B$8*(1+Assumptions!$B$13)-Calc_Barclays!$B$10*(1+Assumptions!$B$12))*(1-Assumptions!$B$14))/(Calc_Barclays!$B$17+(((Calc_Barclays!$B$20+$A6*(1-D$5)*Assumptions!$B$11)*Calc_Barclays!$B$16+Calc_Barclays!$B$8*(1+Assumptions!$B$13)-Calc_Barclays!$B$10*(1+Assumptions!$B$12))*(1-Assumptions!$B$14))/2) -> 0.075776211 | E6: =(((Calc_Barclays!$B$20+$A6*(1-E$5)*Assumptions!$B$11)*Calc_Barclays!$B$16+Calc_Barclays!$B$8*(1+Assumptions!$B$13)-Calc_Barclays!$B$10*(1+Assumptions!$B$12))*(1-Assumptions!$B$14))/(Calc_Barclays!$B$17+(((Calc_Barclays!$B$20+$A6*(1-E$5)*Assumptions!$B$11)*Calc_Barclays!$B$16+Calc_Barclays!$B$8*(1+Assumptions!$B$13)-Calc_Barclays!$B$10*(1+Assumptions!$B$12))*(1-Assumptions!$B$14))/2) -> 0.08072375 | F6: =(((Calc_Barclays!$B$20+$A6*(1-F$5)*Assumptions!$B$11)*Calc_Barclays!$B$16+Calc_Barclays!$B$8*(1+Assumptions!$B$13)-Calc_Barclays!$B$10*(1+Assumptions!$B$12))*(1-Assumptions!$B$14))/(Calc_Barclays!$B$17+(((Calc_Barclays!$B$20+$A6*(1-F$5)*Assumptions!$B$11)*Calc_Barclays!$B$16+Calc_Barclays!$B$8*(1+Assumptions!$B$13)-Calc_Barclays!$B$10*(1+Assumptions!$B$12))*(1-Assumptions!$B$14))/2) -> 0.085645911 | G6: =(((Calc_Barclays!$B$20+$A6*(1-G$5)*Assumptions!$B$11)*Calc_Barclays!$B$16+Calc_Barclays!$B$8*(1+Assumptions!$B$13)-Calc_Barclays!$B$10*(1+Assumptions!$B$12))*(1-Assumptions!$B$14))/(Calc_Barclays!$B$17+(((Calc_Barclays!$B$20+$A6*(1-G$5)*Assumptions!$B$11)*Calc_Barclays!$B$16+Calc_Barclays!$B$8*(1+Assumptions!$B$13)-Calc_Barclays!$B$10*(1+Assumptions!$B$12))*(1-Assumptions!$B$14))/2) -> 0.09054289 | H6: =(((Calc_Barclays!$B$20+$A6*(1-H$5)*Assumptions!$B$11)*Calc_Barclays!$B$16+Calc_Barclays!$B$8*(1+Assumptions!$B$13)-Calc_Barclays!$B$10*(1+Assumptions!$B$12))*(1-Assumptions!$B$14))/(Calc_Barclays!$B$17+(((Calc_Barclays!$B$20+$A6*(1-H$5)*Assumptions!$B$11)*Calc_Barclays!$B$16+Calc_Barclays!$B$8*(1+Assumptions!$B$13)-Calc_Barclays!$B$10*(1+Assumptions!$B$12))*(1-Assumptions!$B$14))/2) -> 0.09541488
A7: -0.0025 | B7: =(((Calc_Barclays!$B$20+$A7*(1-B$5)*Assumptions!$B$11)*Calc_Barclays!$B$16+Calc_Barclays!$B$8*(1+Assumptions!$B$13)-Calc_Barclays!$B$10*(1+Assumptions!$B$12))*(1-Assumptions!$B$14))/(Calc_Barclays!$B$17+(((Calc_Barclays!$B$20+$A7*(1-B$5)*Assumptions!$B$11)*Calc_Barclays!$B$16+Calc_Barclays!$B$8*(1+Assumptions!$B$13)-Calc_Barclays!$B$10*(1+Assumptions!$B$12))*(1-Assumptions!$B$14))/2) -> 0.085645911 | C7: =(((Calc_Barclays!$B$20+$A7*(1-C$5)*Assumptions!$B$11)*Calc_Barclays!$B$16+Calc_Barclays!$B$8*(1+Assumptions!$B$13)-Calc_Barclays!$B$10*(1+Assumptions!$B$12))*(1-Assumptions!$B$14))/(Calc_Barclays!$B$17+(((Calc_Barclays!$B$20+$A7*(1-C$5)*Assumptions!$B$11)*Calc_Barclays!$B$16+Calc_Barclays!$B$8*(1+Assumptions!$B$13)-Calc_Barclays!$B$10*(1+Assumptions!$B$12))*(1-Assumptions!$B$14))/2) -> 0.088097536 | D7: =(((Calc_Barclays!$B$20+$A7*(1-D$5)*Assumptions!$B$11)*Calc_Barclays!$B$16+Calc_Barclays!$B$8*(1+Assumptions!$B$13)-Calc_Barclays!$B$10*(1+Assumptions!$B$12))*(1-Assumptions!$B$14))/(Calc_Barclays!$B$17+(((Calc_Barclays!$B$20+$A7*(1-D$5)*Assumptions!$B$11)*Calc_Barclays!$B$16+Calc_Barclays!$B$8*(1+Assumptions!$B$13)-Calc_Barclays!$B$10*(1+Assumptions!$B$12))*(1-Assumptions!$B$14))/2) -> 0.09054289 | E7: =(((Calc_Barclays!$B$20+$A7*(1-E$5)*Assumptions!$B$11)*Calc_Barclays!$B$16+Calc_Barclays!$B$8*(1+Assumptions!$B$13)-Calc_Barclays!$B$10*(1+Assumptions!$B$12))*(1-Assumptions!$B$14))/(Calc_Barclays!$B$17+(((Calc_Barclays!$B$20+$A7*(1-E$5)*Assumptions!$B$11)*Calc_Barclays!$B$16+Calc_Barclays!$B$8*(1+Assumptions!$B$13)-Calc_Barclays!$B$10*(1+Assumptions!$B$12))*(1-Assumptions!$B$14))/2) -> 0.092981997 | F7: =(((Calc_Barclays!$B$20+$A7*(1-F$5)*Assumptions!$B$11)*Calc_Barclays!$B$16+Calc_Barclays!$B$8*(1+Assumptions!$B$13)-Calc_Barclays!$B$10*(1+Assumptions!$B$12))*(1-Assumptions!$B$14))/(Calc_Barclays!$B$17+(((Calc_Barclays!$B$20+$A7*(1-F$5)*Assumptions!$B$11)*Calc_Barclays!$B$16+Calc_Barclays!$B$8*(1+Assumptions!$B$13)-Calc_Barclays!$B$10*(1+Assumptions!$B$12))*(1-Assumptions!$B$14))/2) -> 0.09541488 | G7: =(((Calc_Barclays!$B$20+$A7*(1-G$5)*Assumptions!$B$11)*Calc_Barclays!$B$16+Calc_Barclays!$B$8*(1+Assumptions!$B$13)-Calc_Barclays!$B$10*(1+Assumptions!$B$12))*(1-Assumptions!$B$14))/(Calc_Barclays!$B$17+(((Calc_Barclays!$B$20+$A7*(1-G$5)*Assumptions!$B$11)*Calc_Barclays!$B$16+Calc_Barclays!$B$8*(1+Assumptions!$B$13)-Calc_Barclays!$B$10*(1+Assumptions!$B$12))*(1-Assumptions!$B$14))/2) -> 0.097841564 | H7: =(((Calc_Barclays!$B$20+$A7*(1-H$5)*Assumptions!$B$11)*Calc_Barclays!$B$16+Calc_Barclays!$B$8*(1+Assumptions!$B$13)-Calc_Barclays!$B$10*(1+Assumptions!$B$12))*(1-Assumptions!$B$14))/(Calc_Barclays!$B$17+(((Calc_Barclays!$B$20+$A7*(1-H$5)*Assumptions!$B$11)*Calc_Barclays!$B$16+Calc_Barclays!$B$8*(1+Assumptions!$B$13)-Calc_Barclays!$B$10*(1+Assumptions!$B$12))*(1-Assumptions!$B$14))/2) -> 0.10026207
A8: 0 | B8: =(((Calc_Barclays!$B$20+$A8*(1-B$5)*Assumptions!$B$11)*Calc_Barclays!$B$16+Calc_Barclays!$B$8*(1+Assumptions!$B$13)-Calc_Barclays!$B$10*(1+Assumptions!$B$12))*(1-Assumptions!$B$14))/(Calc_Barclays!$B$17+(((Calc_Barclays!$B$20+$A8*(1-B$5)*Assumptions!$B$11)*Calc_Barclays!$B$16+Calc_Barclays!$B$8*(1+Assumptions!$B$13)-Calc_Barclays!$B$10*(1+Assumptions!$B$12))*(1-Assumptions!$B$14))/2) -> 0.10508465 | C8: =(((Calc_Barclays!$B$20+$A8*(1-C$5)*Assumptions!$B$11)*Calc_Barclays!$B$16+Calc_Barclays!$B$8*(1+Assumptions!$B$13)-Calc_Barclays!$B$10*(1+Assumptions!$B$12))*(1-Assumptions!$B$14))/(Calc_Barclays!$B$17+(((Calc_Barclays!$B$20+$A8*(1-C$5)*Assumptions!$B$11)*Calc_Barclays!$B$16+Calc_Barclays!$B$8*(1+Assumptions!$B$13)-Calc_Barclays!$B$10*(1+Assumptions!$B$12))*(1-Assumptions!$B$14))/2) -> 0.10508465 | D8: =(((Calc_Barclays!$B$20+$A8*(1-D$5)*Assumptions!$B$11)*Calc_Barclays!$B$16+Calc_Barclays!$B$8*(1+Assumptions!$B$13)-Calc_Barclays!$B$10*(1+Assumptions!$B$12))*(1-Assumptions!$B$14))/(Calc_Barclays!$B$17+(((Calc_Barclays!$B$20+$A8*(1-D$5)*Assumptions!$B$11)*Calc_Barclays!$B$16+Calc_Barclays!$B$8*(1+Assumptions!$B$13)-Calc_Barclays!$B$10*(1+Assumptions!$B$12))*(1-Assumptions!$B$14))/2) -> 0.10508465 | E8: =(((Calc_Barclays!$B$20+$A8*(1-E$5)*Assumptions!$B$11)*Calc_Barclays!$B$16+Calc_Barclays!$B$8*(1+Assumptions!$B$13)-Calc_Barclays!$B$10*(1+Assumptions!$B$12))*(1-Assumptions!$B$14))/(Calc_Barclays!$B$17+(((Calc_Barclays!$B$20+$A8*(1-E$5)*Assumptions!$B$11)*Calc_Barclays!$B$16+Calc_Barclays!$B$8*(1+Assumptions!$B$13)-Calc_Barclays!$B$10*(1+Assumptions!$B$12))*(1-Assumptions!$B$14))/2) -> 0.10508465 | F8: =(((Calc_Barclays!$B$20+$A8*(1-F$5)*Assumptions!$B$11)*Calc_Barclays!$B$16+Calc_Barclays!$B$8*(1+Assumptions!$B$13)-Calc_Barclays!$B$10*(1+Assumptions!$B$12))*(1-Assumptions!$B$14))/(Calc_Barclays!$B$17+(((Calc_Barclays!$B$20+$A8*(1-F$5)*Assumptions!$B$11)*Calc_Barclays!$B$16+Calc_Barclays!$B$8*(1+Assumptions!$B$13)-Calc_Barclays!$B$10*(1+Assumptions!$B$12))*(1-Assumptions!$B$14))/2) -> 0.10508465 | G8: =(((Calc_Barclays!$B$20+$A8*(1-G$5)*Assumptions!$B$11)*Calc_Barclays!$B$16+Calc_Barclays!$B$8*(1+Assumptions!$B$13)-Calc_Barclays!$B$10*(1+Assumptions!$B$12))*(1-Assumptions!$B$14))/(Calc_Barclays!$B$17+(((Calc_Barclays!$B$20+$A8*(1-G$5)*Assumptions!$B$11)*Calc_Barclays!$B$16+Calc_Barclays!$B$8*(1+Assumptions!$B$13)-Calc_Barclays!$B$10*(1+Assumptions!$B$12))*(1-Assumptions!$B$14))/2) -> 0.10508465 | H8: =(((Calc_Barclays!$B$20+$A8*(1-H$5)*Assumptions!$B$11)*Calc_Barclays!$B$16+Calc_Barclays!$B$8*(1+Assumptions!$B$13)-Calc_Barclays!$B$10*(1+Assumptions!$B$12))*(1-Assumptions!$B$14))/(Calc_Barclays!$B$17+(((Calc_Barclays!$B$20+$A8*(1-H$5)*Assumptions!$B$11)*Calc_Barclays!$B$16+Calc_Barclays!$B$8*(1+Assumptions!$B$13)-Calc_Barclays!$B$10*(1+Assumptions!$B$12))*(1-Assumptions!$B$14))/2) -> 0.10508465
A9: 0.0025 | B9: =(((Calc_Barclays!$B$20+$A9*(1-B$5)*Assumptions!$B$11)*Calc_Barclays!$B$16+Calc_Barclays!$B$8*(1+Assumptions!$B$13)-Calc_Barclays!$B$10*(1+Assumptions!$B$12))*(1-Assumptions!$B$14))/(Calc_Barclays!$B$17+(((Calc_Barclays!$B$20+$A9*(1-B$5)*Assumptions!$B$11)*Calc_Barclays!$B$16+Calc_Barclays!$B$8*(1+Assumptions!$B$13)-Calc_Barclays!$B$10*(1+Assumptions!$B$12))*(1-Assumptions!$B$14))/2) -> 0.12413259 | C9: =(((Calc_Barclays!$B$20+$A9*(1-C$5)*Assumptions!$B$11)*Calc_Barclays!$B$16+Calc_Barclays!$B$8*(1+Assumptions!$B$13)-Calc_Barclays!$B$10*(1+Assumptions!$B$12))*(1-Assumptions!$B$14))/(Calc_Barclays!$B$17+(((Calc_Barclays!$B$20+$A9*(1-C$5)*Assumptions!$B$11)*Calc_Barclays!$B$16+Calc_Barclays!$B$8*(1+Assumptions!$B$13)-Calc_Barclays!$B$10*(1+Assumptions!$B$12))*(1-Assumptions!$B$14))/2) -> 0.12177257 | D9: =(((Calc_Barclays!$B$20+$A9*(1-D$5)*Assumptions!$B$11)*Calc_Barclays!$B$16+Calc_Barclays!$B$8*(1+Assumptions!$B$13)-Calc_Barclays!$B$10*(1+Assumptions!$B$12))*(1-Assumptions!$B$14))/(Calc_Barclays!$B$17+(((Calc_Barclays!$B$20+$A9*(1-D$5)*Assumptions!$B$11)*Calc_Barclays!$B$16+Calc_Barclays!$B$8*(1+Assumptions!$B$13)-Calc_Barclays!$B$10*(1+Assumptions!$B$12))*(1-Assumptions!$B$14))/2) -> 0.1194066 | E9: =(((Calc_Barclays!$B$20+$A9*(1-E$5)*Assumptions!$B$11)*Calc_Barclays!$B$16+Calc_Barclays!$B$8*(1+Assumptions!$B$13)-Calc_Barclays!$B$10*(1+Assumptions!$B$12))*(1-Assumptions!$B$14))/(Calc_Barclays!$B$17+(((Calc_Barclays!$B$20+$A9*(1-E$5)*Assumptions!$B$11)*Calc_Barclays!$B$16+Calc_Barclays!$B$8*(1+Assumptions!$B$13)-Calc_Barclays!$B$10*(1+Assumptions!$B$12))*(1-Assumptions!$B$14))/2) -> 0.11703466 | F9: =(((Calc_Barclays!$B$20+$A9*(1-F$5)*Assumptions!$B$11)*Calc_Barclays!$B$16+Calc_Barclays!$B$8*(1+Assumptions!$B$13)-Calc_Barclays!$B$10*(1+Assumptions!$B$12))*(1-Assumptions!$B$14))/(Calc_Barclays!$B$17+(((Calc_Barclays!$B$20+$A9*(1-F$5)*Assumptions!$B$11)*Calc_Barclays!$B$16+Calc_Barclays!$B$8*(1+Assumptions!$B$13)-Calc_Barclays!$B$10*(1+Assumptions!$B$12))*(1-Assumptions!$B$14))/2) -> 0.11465673 | G9: =(((Calc_Barclays!$B$20+$A9*(1-G$5)*Assumptions!$B$11)*Calc_Barclays!$B$16+Calc_Barclays!$B$8*(1+Assumptions!$B$13)-Calc_Barclays!$B$10*(1+Assumptions!$B$12))*(1-Assumptions!$B$14))/(Calc_Barclays!$B$17+(((Calc_Barclays!$B$20+$A9*(1-G$5)*Assumptions!$B$11)*Calc_Barclays!$B$16+Calc_Barclays!$B$8*(1+Assumptions!$B$13)-Calc_Barclays!$B$10*(1+Assumptions!$B$12))*(1-Assumptions!$B$14))/2) -> 0.11227279 | H9: =(((Calc_Barclays!$B$20+$A9*(1-H$5)*Assumptions!$B$11)*Calc_Barclays!$B$16+Calc_Barclays!$B$8*(1+Assumptions!$B$13)-Calc_Barclays!$B$10*(1+Assumptions!$B$12))*(1-Assumptions!$B$14))/(Calc_Barclays!$B$17+(((Calc_Barclays!$B$20+$A9*(1-H$5)*Assumptions!$B$11)*Calc_Barclays!$B$16+Calc_Barclays!$B$8*(1+Assumptions!$B$13)-Calc_Barclays!$B$10*(1+Assumptions!$B$12))*(1-Assumptions!$B$14))/2) -> 0.10988281
A10: 0.005 | B10: =(((Calc_Barclays!$B$20+$A10*(1-B$5)*Assumptions!$B$11)*Calc_Barclays!$B$16+Calc_Barclays!$B$8*(1+Assumptions!$B$13)-Calc_Barclays!$B$10*(1+Assumptions!$B$12))*(1-Assumptions!$B$14))/(Calc_Barclays!$B$17+(((Calc_Barclays!$B$20+$A10*(1-B$5)*Assumptions!$B$11)*Calc_Barclays!$B$16+Calc_Barclays!$B$8*(1+Assumptions!$B$13)-Calc_Barclays!$B$10*(1+Assumptions!$B$12))*(1-Assumptions!$B$14))/2) -> 0.1428014 | C10: =(((Calc_Barclays!$B$20+$A10*(1-C$5)*Assumptions!$B$11)*Calc_Barclays!$B$16+Calc_Barclays!$B$8*(1+Assumptions!$B$13)-Calc_Barclays!$B$10*(1+Assumptions!$B$12))*(1-Assumptions!$B$14))/(Calc_Barclays!$B$17+(((Calc_Barclays!$B$20+$A10*(1-C$5)*Assumptions!$B$11)*Calc_Barclays!$B$16+Calc_Barclays!$B$8*(1+Assumptions!$B$13)-Calc_Barclays!$B$10*(1+Assumptions!$B$12))*(1-Assumptions!$B$14))/2) -> 0.13816912 | D10: =(((Calc_Barclays!$B$20+$A10*(1-D$5)*Assumptions!$B$11)*Calc_Barclays!$B$16+Calc_Barclays!$B$8*(1+Assumptions!$B$13)-Calc_Barclays!$B$10*(1+Assumptions!$B$12))*(1-Assumptions!$B$14))/(Calc_Barclays!$B$17+(((Calc_Barclays!$B$20+$A10*(1-D$5)*Assumptions!$B$11)*Calc_Barclays!$B$16+Calc_Barclays!$B$8*(1+Assumptions!$B$13)-Calc_Barclays!$B$10*(1+Assumptions!$B$12))*(1-Assumptions!$B$14))/2) -> 0.13351368 | E10: =(((Calc_Barclays!$B$20+$A10*(1-E$5)*Assumptions!$B$11)*Calc_Barclays!$B$16+Calc_Barclays!$B$8*(1+Assumptions!$B$13)-Calc_Barclays!$B$10*(1+Assumptions!$B$12))*(1-Assumptions!$B$14))/(Calc_Barclays!$B$17+(((Calc_Barclays!$B$20+$A10*(1-E$5)*Assumptions!$B$11)*Calc_Barclays!$B$16+Calc_Barclays!$B$8*(1+Assumptions!$B$13)-Calc_Barclays!$B$10*(1+Assumptions!$B$12))*(1-Assumptions!$B$14))/2) -> 0.12883489 | F10: =(((Calc_Barclays!$B$20+$A10*(1-F$5)*Assumptions!$B$11)*Calc_Barclays!$B$16+Calc_Barclays!$B$8*(1+Assumptions!$B$13)-Calc_Barclays!$B$10*(1+Assumptions!$B$12))*(1-Assumptions!$B$14))/(Calc_Barclays!$B$17+(((Calc_Barclays!$B$20+$A10*(1-F$5)*Assumptions!$B$11)*Calc_Barclays!$B$16+Calc_Barclays!$B$8*(1+Assumptions!$B$13)-Calc_Barclays!$B$10*(1+Assumptions!$B$12))*(1-Assumptions!$B$14))/2) -> 0.12413259 | G10: =(((Calc_Barclays!$B$20+$A10*(1-G$5)*Assumptions!$B$11)*Calc_Barclays!$B$16+Calc_Barclays!$B$8*(1+Assumptions!$B$13)-Calc_Barclays!$B$10*(1+Assumptions!$B$12))*(1-Assumptions!$B$14))/(Calc_Barclays!$B$17+(((Calc_Barclays!$B$20+$A10*(1-G$5)*Assumptions!$B$11)*Calc_Barclays!$B$16+Calc_Barclays!$B$8*(1+Assumptions!$B$13)-Calc_Barclays!$B$10*(1+Assumptions!$B$12))*(1-Assumptions!$B$14))/2) -> 0.1194066 | H10: =(((Calc_Barclays!$B$20+$A10*(1-H$5)*Assumptions!$B$11)*Calc_Barclays!$B$16+Calc_Barclays!$B$8*(1+Assumptions!$B$13)-Calc_Barclays!$B$10*(1+Assumptions!$B$12))*(1-Assumptions!$B$14))/(Calc_Barclays!$B$17+(((Calc_Barclays!$B$20+$A10*(1-H$5)*Assumptions!$B$11)*Calc_Barclays!$B$16+Calc_Barclays!$B$8*(1+Assumptions!$B$13)-Calc_Barclays!$B$10*(1+Assumptions!$B$12))*(1-Assumptions!$B$14))/2) -> 0.11465673
A13: BNP Paribas (ECB, Lag 60%, Tax 26.5%)
A14: ΔRate \ β | B14: 0.2 | C14: 0.3 | D14: 0.4 | E14: 0.5 | F14: 0.6 | G14: 0.7 | H14: 0.8
A15: -0.005 | B15: =(((Calc_BNP!$B$20+$A15*(1-B$14)*Assumptions!$C$11)*Calc_BNP!$B$16+Calc_BNP!$B$8*(1+Assumptions!$C$13)-Calc_BNP!$B$10*(1+Assumptions!$C$12))*(1-Assumptions!$C$14))/(Calc_BNP!$B$17+(((Calc_BNP!$B$20+$A15*(1-B$14)*Assumptions!$C$11)*Calc_BNP!$B$16+Calc_BNP!$B$8*(1+Assumptions!$C$13)-Calc_BNP!$B$10*(1+Assumptions!$C$12))*(1-Assumptions!$C$14))/2) -> 0.066296243 | C15: =(((Calc_BNP!$B$20+$A15*(1-C$14)*Assumptions!$C$11)*Calc_BNP!$B$16+Calc_BNP!$B$8*(1+Assumptions!$C$13)-Calc_BNP!$B$10*(1+Assumptions!$C$12))*(1-Assumptions!$C$14))/(Calc_BNP!$B$17+(((Calc_BNP!$B$20+$A15*(1-C$14)*Assumptions!$C$11)*Calc_BNP!$B$16+Calc_BNP!$B$8*(1+Assumptions!$C$13)-Calc_BNP!$B$10*(1+Assumptions!$C$12))*(1-Assumptions!$C$14))/2) -> 0.070637648 | D15: =(((Calc_BNP!$B$20+$A15*(1-D$14)*Assumptions!$C$11)*Calc_BNP!$B$16+Calc_BNP!$B$8*(1+Assumptions!$C$13)-Calc_BNP!$B$10*(1+Assumptions!$C$12))*(1-Assumptions!$C$14))/(Calc_BNP!$B$17+(((Calc_BNP!$B$20+$A15*(1-D$14)*Assumptions!$C$11)*Calc_BNP!$B$16+Calc_BNP!$B$8*(1+Assumptions!$C$13)-Calc_BNP!$B$10*(1+Assumptions!$C$12))*(1-Assumptions!$C$14))/2) -> 0.074959603 | E15: =(((Calc_BNP!$B$20+$A15*(1-E$14)*Assumptions!$C$11)*Calc_BNP!$B$16+Calc_BNP!$B$8*(1+Assumptions!$C$13)-Calc_BNP!$B$10*(1+Assumptions!$C$12))*(1-Assumptions!$C$14))/(Calc_BNP!$B$17+(((Calc_BNP!$B$20+$A15*(1-E$14)*Assumptions!$C$11)*Calc_BNP!$B$16+Calc_BNP!$B$8*(1+Assumptions!$C$13)-Calc_BNP!$B$10*(1+Assumptions!$C$12))*(1-Assumptions!$C$14))/2) -> 0.079262237 | F15: =(((Calc_BNP!$B$20+$A15*(1-F$14)*Assumptions!$C$11)*Calc_BNP!$B$16+Calc_BNP!$B$8*(1+Assumptions!$C$13)-Calc_BNP!$B$10*(1+Assumptions!$C$12))*(1-Assumptions!$C$14))/(Calc_BNP!$B$17+(((Calc_BNP!$B$20+$A15*(1-F$14)*Assumptions!$C$11)*Calc_BNP!$B$16+Calc_BNP!$B$8*(1+Assumptions!$C$13)-Calc_BNP!$B$10*(1+Assumptions!$C$12))*(1-Assumptions!$C$14))/2) -> 0.083545681 | G15: =(((Calc_BNP!$B$20+$A15*(1-G$14)*Assumptions!$C$11)*Calc_BNP!$B$16+Calc_BNP!$B$8*(1+Assumptions!$C$13)-Calc_BNP!$B$10*(1+Assumptions!$C$12))*(1-Assumptions!$C$14))/(Calc_BNP!$B$17+(((Calc_BNP!$B$20+$A15*(1-G$14)*Assumptions!$C$11)*Calc_BNP!$B$16+Calc_BNP!$B$8*(1+Assumptions!$C$13)-Calc_BNP!$B$10*(1+Assumptions!$C$12))*(1-Assumptions!$C$14))/2) -> 0.087810063 | H15: =(((Calc_BNP!$B$20+$A15*(1-H$14)*Assumptions!$C$11)*Calc_BNP!$B$16+Calc_BNP!$B$8*(1+Assumptions!$C$13)-Calc_BNP!$B$10*(1+Assumptions!$C$12))*(1-Assumptions!$C$14))/(Calc_BNP!$B$17+(((Calc_BNP!$B$20+$A15*(1-H$14)*Assumptions!$C$11)*Calc_BNP!$B$16+Calc_BNP!$B$8*(1+Assumptions!$C$13)-Calc_BNP!$B$10*(1+Assumptions!$C$12))*(1-Assumptions!$C$14))/2) -> 0.092055509
A16: -0.0025 | B16: =(((Calc_BNP!$B$20+$A16*(1-B$14)*Assumptions!$C$11)*Calc_BNP!$B$16+Calc_BNP!$B$8*(1+Assumptions!$C$13)-Calc_BNP!$B$10*(1+Assumptions!$C$12))*(1-Assumptions!$C$14))/(Calc_BNP!$B$17+(((Calc_BNP!$B$20+$A16*(1-B$14)*Assumptions!$C$11)*Calc_BNP!$B$16+Calc_BNP!$B$8*(1+Assumptions!$C$13)-Calc_BNP!$B$10*(1+Assumptions!$C$12))*(1-Assumptions!$C$14))/2) -> 0.083545681 | C16: =(((Calc_BNP!$B$20+$A16*(1-C$14)*Assumptions!$C$11)*Calc_BNP!$B$16+Calc_BNP!$B$8*(1+Assumptions!$C$13)-Calc_BNP!$B$10*(1+Assumptions!$C$12))*(1-Assumptions!$C$14))/(Calc_BNP!$B$17+(((Calc_BNP!$B$20+$A16*(1-C$14)*Assumptions!$C$11)*Calc_BNP!$B$16+Calc_BNP!$B$8*(1+Assumptions!$C$13)-Calc_BNP!$B$10*(1+Assumptions!$C$12))*(1-Assumptions!$C$14))/2) -> 0.085680247 | D16: =(((Calc_BNP!$B$20+$A16*(1-D$14)*Assumptions!$C$11)*Calc_BNP!$B$16+Calc_BNP!$B$8*(1+Assumptions!$C$13)-Calc_BNP!$B$10*(1+Assumptions!$C$12))*(1-Assumptions!$C$14))/(Calc_BNP!$B$17+(((Calc_BNP!$B$20+$A16*(1-D$14)*Assumptions!$C$11)*Calc_BNP!$B$16+Calc_BNP!$B$8*(1+Assumptions!$C$13)-Calc_BNP!$B$10*(1+Assumptions!$C$12))*(1-Assumptions!$C$14))/2) -> 0.087810063 | E16: =(((Calc_BNP!$B$20+$A16*(1-E$14)*Assumptions!$C$11)*Calc_BNP!$B$16+Calc_BNP!$B$8*(1+Assumptions!$C$13)-Calc_BNP!$B$10*(1+Assumptions!$C$12))*(1-Assumptions!$C$14))/(Calc_BNP!$B$17+(((Calc_BNP!$B$20+$A16*(1-E$14)*Assumptions!$C$11)*Calc_BNP!$B$16+Calc_BNP!$B$8*(1+Assumptions!$C$13)-Calc_BNP!$B$10*(1+Assumptions!$C$12))*(1-Assumptions!$C$14))/2) -> 0.089935145 | F16: =(((Calc_BNP!$B$20+$A16*(1-F$14)*Assumptions!$C$11)*Calc_BNP!$B$16+Calc_BNP!$B$8*(1+Assumptions!$C$13)-Calc_BNP!$B$10*(1+Assumptions!$C$12))*(1-Assumptions!$C$14))/(Calc_BNP!$B$17+(((Calc_BNP!$B$20+$A16*(1-F$14)*Assumptions!$C$11)*Calc_BNP!$B$16+Calc_BNP!$B$8*(1+Assumptions!$C$13)-Calc_BNP!$B$10*(1+Assumptions!$C$12))*(1-Assumptions!$C$14))/2) -> 0.092055509 | G16: =(((Calc_BNP!$B$20+$A16*(1-G$14)*Assumptions!$C$11)*Calc_BNP!$B$16+Calc_BNP!$B$8*(1+Assumptions!$C$13)-Calc_BNP!$B$10*(1+Assumptions!$C$12))*(1-Assumptions!$C$14))/(Calc_BNP!$B$17+(((Calc_BNP!$B$20+$A16*(1-G$14)*Assumptions!$C$11)*Calc_BNP!$B$16+Calc_BNP!$B$8*(1+Assumptions!$C$13)-Calc_BNP!$B$10*(1+Assumptions!$C$12))*(1-Assumptions!$C$14))/2) -> 0.09417117 | H16: =(((Calc_BNP!$B$20+$A16*(1-H$14)*Assumptions!$C$11)*Calc_BNP!$B$16+Calc_BNP!$B$8*(1+Assumptions!$C$13)-Calc_BNP!$B$10*(1+Assumptions!$C$12))*(1-Assumptions!$C$14))/(Calc_BNP!$B$17+(((Calc_BNP!$B$20+$A16*(1-H$14)*Assumptions!$C$11)*Calc_BNP!$B$16+Calc_BNP!$B$8*(1+Assumptions!$C$13)-Calc_BNP!$B$10*(1+Assumptions!$C$12))*(1-Assumptions!$C$14))/2) -> 0.096282145
A17: 0 | B17: =(((Calc_BNP!$B$20+$A17*(1-B$14)*Assumptions!$C$11)*Calc_BNP!$B$16+Calc_BNP!$B$8*(1+Assumptions!$C$13)-Calc_BNP!$B$10*(1+Assumptions!$C$12))*(1-Assumptions!$C$14))/(Calc_BNP!$B$17+(((Calc_BNP!$B$20+$A17*(1-B$14)*Assumptions!$C$11)*Calc_BNP!$B$16+Calc_BNP!$B$8*(1+Assumptions!$C$13)-Calc_BNP!$B$10*(1+Assumptions!$C$12))*(1-Assumptions!$C$14))/2) -> 0.1004901 | C17: =(((Calc_BNP!$B$20+$A17*(1-C$14)*Assumptions!$C$11)*Calc_BNP!$B$16+Calc_BNP!$B$8*(1+Assumptions!$C$13)-Calc_BNP!$B$10*(1+Assumptions!$C$12))*(1-Assumptions!$C$14))/(Calc_BNP!$B$17+(((Calc_BNP!$B$20+$A17*(1-C$14)*Assumptions!$C$11)*Calc_BNP!$B$16+Calc_BNP!$B$8*(1+Assumptions!$C$13)-Calc_BNP!$B$10*(1+Assumptions!$C$12))*(1-Assumptions!$C$14))/2) -> 0.1004901 | D17: =(((Calc_BNP!$B$20+$A17*(1-D$14)*Assumptions!$C$11)*Calc_BNP!$B$16+Calc_BNP!$B$8*(1+Assumptions!$C$13)-Calc_BNP!$B$10*(1+Assumptions!$C$12))*(1-Assumptions!$C$14))/(Calc_BNP!$B$17+(((Calc_BNP!$B$20+$A17*(1-D$14)*Assumptions!$C$11)*Calc_BNP!$B$16+Calc_BNP!$B$8*(1+Assumptions!$C$13)-Calc_BNP!$B$10*(1+Assumptions!$C$12))*(1-Assumptions!$C$14))/2) -> 0.1004901 | E17: =(((Calc_BNP!$B$20+$A17*(1-E$14)*Assumptions!$C$11)*Calc_BNP!$B$16+Calc_BNP!$B$8*(1+Assumptions!$C$13)-Calc_BNP!$B$10*(1+Assumptions!$C$12))*(1-Assumptions!$C$14))/(Calc_BNP!$B$17+(((Calc_BNP!$B$20+$A17*(1-E$14)*Assumptions!$C$11)*Calc_BNP!$B$16+Calc_BNP!$B$8*(1+Assumptions!$C$13)-Calc_BNP!$B$10*(1+Assumptions!$C$12))*(1-Assumptions!$C$14))/2) -> 0.1004901 | F17: =(((Calc_BNP!$B$20+$A17*(1-F$14)*Assumptions!$C$11)*Calc_BNP!$B$16+Calc_BNP!$B$8*(1+Assumptions!$C$13)-Calc_BNP!$B$10*(1+Assumptions!$C$12))*(1-Assumptions!$C$14))/(Calc_BNP!$B$17+(((Calc_BNP!$B$20+$A17*(1-F$14)*Assumptions!$C$11)*Calc_BNP!$B$16+Calc_BNP!$B$8*(1+Assumptions!$C$13)-Calc_BNP!$B$10*(1+Assumptions!$C$12))*(1-Assumptions!$C$14))/2) -> 0.1004901 | G17: =(((Calc_BNP!$B$20+$A17*(1-G$14)*Assumptions!$C$11)*Calc_BNP!$B$16+Calc_BNP!$B$8*(1+Assumptions!$C$13)-Calc_BNP!$B$10*(1+Assumptions!$C$12))*(1-Assumptions!$C$14))/(Calc_BNP!$B$17+(((Calc_BNP!$B$20+$A17*(1-G$14)*Assumptions!$C$11)*Calc_BNP!$B$16+Calc_BNP!$B$8*(1+Assumptions!$C$13)-Calc_BNP!$B$10*(1+Assumptions!$C$12))*(1-Assumptions!$C$14))/2) -> 0.1004901 | H17: =(((Calc_BNP!$B$20+$A17*(1-H$14)*Assumptions!$C$11)*Calc_BNP!$B$16+Calc_BNP!$B$8*(1+Assumptions!$C$13)-Calc_BNP!$B$10*(1+Assumptions!$C$12))*(1-Assumptions!$C$14))/(Calc_BNP!$B$17+(((Calc_BNP!$B$20+$A17*(1-H$14)*Assumptions!$C$11)*Calc_BNP!$B$16+Calc_BNP!$B$8*(1+Assumptions!$C$13)-Calc_BNP!$B$10*(1+Assumptions!$C$12))*(1-Assumptions!$C$14))/2) -> 0.1004901
A18: 0.0025 | B18: =(((Calc_BNP!$B$20+$A18*(1-B$14)*Assumptions!$C$11)*Calc_BNP!$B$16+Calc_BNP!$B$8*(1+Assumptions!$C$13)-Calc_BNP!$B$10*(1+Assumptions!$C$12))*(1-Assumptions!$C$14))/(Calc_BNP!$B$17+(((Calc_BNP!$B$20+$A18*(1-B$14)*Assumptions!$C$11)*Calc_BNP!$B$16+Calc_BNP!$B$8*(1+Assumptions!$C$13)-Calc_BNP!$B$10*(1+Assumptions!$C$12))*(1-Assumptions!$C$14))/2) -> 0.11713751 | C18: =(((Calc_BNP!$B$20+$A18*(1-C$14)*Assumptions!$C$11)*Calc_BNP!$B$16+Calc_BNP!$B$8*(1+Assumptions!$C$13)-Calc_BNP!$B$10*(1+Assumptions!$C$12))*(1-Assumptions!$C$14))/(Calc_BNP!$B$17+(((Calc_BNP!$B$20+$A18*(1-C$14)*Assumptions!$C$11)*Calc_BNP!$B$16+Calc_BNP!$B$8*(1+Assumptions!$C$13)-Calc_BNP!$B$10*(1+Assumptions!$C$12))*(1-Assumptions!$C$14))/2) -> 0.11507256 | D18: =(((Calc_BNP!$B$20+$A18*(1-D$14)*Assumptions!$C$11)*Calc_BNP!$B$16+Calc_BNP!$B$8*(1+Assumptions!$C$13)-Calc_BNP!$B$10*(1+Assumptions!$C$12))*(1-Assumptions!$C$14))/(Calc_BNP!$B$17+(((Calc_BNP!$B$20+$A18*(1-D$14)*Assumptions!$C$11)*Calc_BNP!$B$16+Calc_BNP!$B$8*(1+Assumptions!$C$13)-Calc_BNP!$B$10*(1+Assumptions!$C$12))*(1-Assumptions!$C$14))/2) -> 0.11300307 | E18: =(((Calc_BNP!$B$20+$A18*(1-E$14)*Assumptions!$C$11)*Calc_BNP!$B$16+Calc_BNP!$B$8*(1+Assumptions!$C$13)-Calc_BNP!$B$10*(1+Assumptions!$C$12))*(1-Assumptions!$C$14))/(Calc_BNP!$B$17+(((Calc_BNP!$B$20+$A18*(1-E$14)*Assumptions!$C$11)*Calc_BNP!$B$16+Calc_BNP!$B$8*(1+Assumptions!$C$13)-Calc_BNP!$B$10*(1+Assumptions!$C$12))*(1-Assumptions!$C$14))/2) -> 0.11092904 | F18: =(((Calc_BNP!$B$20+$A18*(1-F$14)*Assumptions!$C$11)*Calc_BNP!$B$16+Calc_BNP!$B$8*(1+Assumptions!$C$13)-Calc_BNP!$B$10*(1+Assumptions!$C$12))*(1-Assumptions!$C$14))/(Calc_BNP!$B$17+(((Calc_BNP!$B$20+$A18*(1-F$14)*Assumptions!$C$11)*Calc_BNP!$B$16+Calc_BNP!$B$8*(1+Assumptions!$C$13)-Calc_BNP!$B$10*(1+Assumptions!$C$12))*(1-Assumptions!$C$14))/2) -> 0.10885044 | G18: =(((Calc_BNP!$B$20+$A18*(1-G$14)*Assumptions!$C$11)*Calc_BNP!$B$16+Calc_BNP!$B$8*(1+Assumptions!$C$13)-Calc_BNP!$B$10*(1+Assumptions!$C$12))*(1-Assumptions!$C$14))/(Calc_BNP!$B$17+(((Calc_BNP!$B$20+$A18*(1-G$14)*Assumptions!$C$11)*Calc_BNP!$B$16+Calc_BNP!$B$8*(1+Assumptions!$C$13)-Calc_BNP!$B$10*(1+Assumptions!$C$12))*(1-Assumptions!$C$14))/2) -> 0.10676726 | H18: =(((Calc_BNP!$B$20+$A18*(1-H$14)*Assumptions!$C$11)*Calc_BNP!$B$16+Calc_BNP!$B$8*(1+Assumptions!$C$13)-Calc_BNP!$B$10*(1+Assumptions!$C$12))*(1-Assumptions!$C$14))/(Calc_BNP!$B$17+(((Calc_BNP!$B$20+$A18*(1-H$14)*Assumptions!$C$11)*Calc_BNP!$B$16+Calc_BNP!$B$8*(1+Assumptions!$C$13)-Calc_BNP!$B$10*(1+Assumptions!$C$12))*(1-Assumptions!$C$14))/2) -> 0.10467949
A19: 0.005 | B19: =(((Calc_BNP!$B$20+$A19*(1-B$14)*Assumptions!$C$11)*Calc_BNP!$B$16+Calc_BNP!$B$8*(1+Assumptions!$C$13)-Calc_BNP!$B$10*(1+Assumptions!$C$12))*(1-Assumptions!$C$14))/(Calc_BNP!$B$17+(((Calc_BNP!$B$20+$A19*(1-B$14)*Assumptions!$C$11)*Calc_BNP!$B$16+Calc_BNP!$B$8*(1+Assumptions!$C$13)-Calc_BNP!$B$10*(1+Assumptions!$C$12))*(1-Assumptions!$C$14))/2) -> 0.13349566 | C19: =(((Calc_BNP!$B$20+$A19*(1-C$14)*Assumptions!$C$11)*Calc_BNP!$B$16+Calc_BNP!$B$8*(1+Assumptions!$C$13)-Calc_BNP!$B$10*(1+Assumptions!$C$12))*(1-Assumptions!$C$14))/(Calc_BNP!$B$17+(((Calc_BNP!$B$20+$A19*(1-C$14)*Assumptions!$C$11)*Calc_BNP!$B$16+Calc_BNP!$B$8*(1+Assumptions!$C$13)-Calc_BNP!$B$10*(1+Assumptions!$C$12))*(1-Assumptions!$C$14))/2) -> 0.12943282 | D19: =(((Calc_BNP!$B$20+$A19*(1-D$14)*Assumptions!$C$11)*Calc_BNP!$B$16+Calc_BNP!$B$8*(1+Assumptions!$C$13)-Calc_BNP!$B$10*(1+Assumptions!$C$12))*(1-Assumptions!$C$14))/(Calc_BNP!$B$17+(((Calc_BNP!$B$20+$A19*(1-D$14)*Assumptions!$C$11)*Calc_BNP!$B$16+Calc_BNP!$B$8*(1+Assumptions!$C$13)-Calc_BNP!$B$10*(1+Assumptions!$C$12))*(1-Assumptions!$C$14))/2) -> 0.12535227 | E19: =(((Calc_BNP!$B$20+$A19*(1-E$14)*Assumptions!$C$11)*Calc_BNP!$B$16+Calc_BNP!$B$8*(1+Assumptions!$C$13)-Calc_BNP!$B$10*(1+Assumptions!$C$12))*(1-Assumptions!$C$14))/(Calc_BNP!$B$17+(((Calc_BNP!$B$20+$A19*(1-E$14)*Assumptions!$C$11)*Calc_BNP!$B$16+Calc_BNP!$B$8*(1+Assumptions!$C$13)-Calc_BNP!$B$10*(1+Assumptions!$C$12))*(1-Assumptions!$C$14))/2) -> 0.12125387 | F19: =(((Calc_BNP!$B$20+$A19*(1-F$14)*Assumptions!$C$11)*Calc_BNP!$B$16+Calc_BNP!$B$8*(1+Assumptions!$C$13)-Calc_BNP!$B$10*(1+Assumptions!$C$12))*(1-Assumptions!$C$14))/(Calc_BNP!$B$17+(((Calc_BNP!$B$20+$A19*(1-F$14)*Assumptions!$C$11)*Calc_BNP!$B$16+Calc_BNP!$B$8*(1+Assumptions!$C$13)-Calc_BNP!$B$10*(1+Assumptions!$C$12))*(1-Assumptions!$C$14))/2) -> 0.11713751 | G19: =(((Calc_BNP!$B$20+$A19*(1-G$14)*Assumptions!$C$11)*Calc_BNP!$B$16+Calc_BNP!$B$8*(1+Assumptions!$C$13)-Calc_BNP!$B$10*(1+Assumptions!$C$12))*(1-Assumptions!$C$14))/(Calc_BNP!$B$17+(((Calc_BNP!$B$20+$A19*(1-G$14)*Assumptions!$C$11)*Calc_BNP!$B$16+Calc_BNP!$B$8*(1+Assumptions!$C$13)-Calc_BNP!$B$10*(1+Assumptions!$C$12))*(1-Assumptions!$C$14))/2) -> 0.11300307 | H19: =(((Calc_BNP!$B$20+$A19*(1-H$14)*Assumptions!$C$11)*Calc_BNP!$B$16+Calc_BNP!$B$8*(1+Assumptions!$C$13)-Calc_BNP!$B$10*(1+Assumptions!$C$12))*(1-Assumptions!$C$14))/(Calc_BNP!$B$17+(((Calc_BNP!$B$20+$A19*(1-H$14)*Assumptions!$C$11)*Calc_BNP!$B$16+Calc_BNP!$B$8*(1+Assumptions!$C$13)-Calc_BNP!$B$10*(1+Assumptions!$C$12))*(1-Assumptions!$C$14))/2) -> 0.10885044
A22: Deutsche Bank (ECB, Lag 70%, Tax 33.8% effective)
A23: ΔRate \ β | B23: 0.2 | C23: 0.3 | D23: 0.4 | E23: 0.5 | F23: 0.6 | G23: 0.7 | H23: 0.8
A24: -0.005 | B24: =(((Calc_Deutsche!$B$20+$A24*(1-B$23)*Assumptions!$D$11)*Calc_Deutsche!$B$16+Calc_Deutsche!$B$8*(1+Assumptions!$D$13)-Calc_Deutsche!$B$10*(1+Assumptions!$D$12))*(1-Calc_Deutsche!$B$21))/(Calc_Deutsche!$B$17+(((Calc_Deutsche!$B$20+$A24*(1-B$23)*Assumptions!$D$11)*Calc_Deutsche!$B$16+Calc_Deutsche!$B$8*(1+Assumptions!$D$13)-Calc_Deutsche!$B$10*(1+Assumptions!$D$12))*(1-Calc_Deutsche!$B$21))/2) -> 0.066824931 | C24: =(((Calc_Deutsche!$B$20+$A24*(1-C$23)*Assumptions!$D$11)*Calc_Deutsche!$B$16+Calc_Deutsche!$B$8*(1+Assumptions!$D$13)-Calc_Deutsche!$B$10*(1+Assumptions!$D$12))*(1-Calc_Deutsche!$B$21))/(Calc_Deutsche!$B$17+(((Calc_Deutsche!$B$20+$A24*(1-C$23)*Assumptions!$D$11)*Calc_Deutsche!$B$16+Calc_Deutsche!$B$8*(1+Assumptions!$D$13)-Calc_Deutsche!$B$10*(1+Assumptions!$D$12))*(1-Calc_Deutsche!$B$21))/2) -> 0.070678306 | D24: =(((Calc_Deutsche!$B$20+$A24*(1-D$23)*Assumptions!$D$11)*Calc_Deutsche!$B$16+Calc_Deutsche!$B$8*(1+Assumptions!$D$13)-Calc_Deutsche!$B$10*(1+Assumptions!$D$12))*(1-Calc_Deutsche!$B$21))/(Calc_Deutsche!$B$17+(((Calc_Deutsche!$B$20+$A24*(1-D$23)*Assumptions!$D$11)*Calc_Deutsche!$B$16+Calc_Deutsche!$B$8*(1+Assumptions!$D$13)-Calc_Deutsche!$B$10*(1+Assumptions!$D$12))*(1-Calc_Deutsche!$B$21))/2) -> 0.07451635 | E24: =(((Calc_Deutsche!$B$20+$A24*(1-E$23)*Assumptions!$D$11)*Calc_Deutsche!$B$16+Calc_Deutsche!$B$8*(1+Assumptions!$D$13)-Calc_Deutsche!$B$10*(1+Assumptions!$D$12))*(1-Calc_Deutsche!$B$21))/(Calc_Deutsche!$B$17+(((Calc_Deutsche!$B$20+$A24*(1-E$23)*Assumptions!$D$11)*Calc_Deutsche!$B$16+Calc_Deutsche!$B$8*(1+Assumptions!$D$13)-Calc_Deutsche!$B$10*(1+Assumptions!$D$12))*(1-Calc_Deutsche!$B$21))/2) -> 0.078339154 | F24: =(((Calc_Deutsche!$B$20+$A24*(1-F$23)*Assumptions!$D$11)*Calc_Deutsche!$B$16+Calc_Deutsche!$B$8*(1+Assumptions!$D$13)-Calc_Deutsche!$B$10*(1+Assumptions!$D$12))*(1-Calc_Deutsche!$B$21))/(Calc_Deutsche!$B$17+(((Calc_Deutsche!$B$20+$A24*(1-F$23)*Assumptions!$D$11)*Calc_Deutsche!$B$16+Calc_Deutsche!$B$8*(1+Assumptions!$D$13)-Calc_Deutsche!$B$10*(1+Assumptions!$D$12))*(1-Calc_Deutsche!$B$21))/2) -> 0.082146809 | G24: =(((Calc_Deutsche!$B$20+$A24*(1-G$23)*Assumptions!$D$11)*Calc_Deutsche!$B$16+Calc_Deutsche!$B$8*(1+Assumptions!$D$13)-Calc_Deutsche!$B$10*(1+Assumptions!$D$12))*(1-Calc_Deutsche!$B$21))/(Calc_Deutsche!$B$17+(((Calc_Deutsche!$B$20+$A24*(1-G$23)*Assumptions!$D$11)*Calc_Deutsche!$B$16+Calc_Deutsche!$B$8*(1+Assumptions!$D$13)-Calc_Deutsche!$B$10*(1+Assumptions!$D$12))*(1-Calc_Deutsche!$B$21))/2) -> 0.085939405 | H24: =(((Calc_Deutsche!$B$20+$A24*(1-H$23)*Assumptions!$D$11)*Calc_Deutsche!$B$16+Calc_Deutsche!$B$8*(1+Assumptions!$D$13)-Calc_Deutsche!$B$10*(1+Assumptions!$D$12))*(1-Calc_Deutsche!$B$21))/(Calc_Deutsche!$B$17+(((Calc_Deutsche!$B$20+$A24*(1-H$23)*Assumptions!$D$11)*Calc_Deutsche!$B$16+Calc_Deutsche!$B$8*(1+Assumptions!$D$13)-Calc_Deutsche!$B$10*(1+Assumptions!$D$12))*(1-Calc_Deutsche!$B$21))/2) -> 0.08971703
A25: -0.0025 | B25: =(((Calc_Deutsche!$B$20+$A25*(1-B$23)*Assumptions!$D$11)*Calc_Deutsche!$B$16+Calc_Deutsche!$B$8*(1+Assumptions!$D$13)-Calc_Deutsche!$B$10*(1+Assumptions!$D$12))*(1-Calc_Deutsche!$B$21))/(Calc_Deutsche!$B$17+(((Calc_Deutsche!$B$20+$A25*(1-B$23)*Assumptions!$D$11)*Calc_Deutsche!$B$16+Calc_Deutsche!$B$8*(1+Assumptions!$D$13)-Calc_Deutsche!$B$10*(1+Assumptions!$D$12))*(1-Calc_Deutsche!$B$21))/2) -> 0.082146809 | C25: =(((Calc_Deutsche!$B$20+$A25*(1-C$23)*Assumptions!$D$11)*Calc_Deutsche!$B$16+Calc_Deutsche!$B$8*(1+Assumptions!$D$13)-Calc_Deutsche!$B$10*(1+Assumptions!$D$12))*(1-Calc_Deutsche!$B$21))/(Calc_Deutsche!$B$17+(((Calc_Deutsche!$B$20+$A25*(1-C$23)*Assumptions!$D$11)*Calc_Deutsche!$B$16+Calc_Deutsche!$B$8*(1+Assumptions!$D$13)-Calc_Deutsche!$B$10*(1+Assumptions!$D$12))*(1-Calc_Deutsche!$B$21))/2) -> 0.084044984 | D25: =(((Calc_Deutsche!$B$20+$A25*(1-D$23)*Assumptions!$D$11)*Calc_Deutsche!$B$16+Calc_Deutsche!$B$8*(1+Assumptions!$D$13)-Calc_Deutsche!$B$10*(1+Assumptions!$D$12))*(1-Calc_Deutsche!$B$21))/(Calc_Deutsche!$B$17+(((Calc_Deutsche!$B$20+$A25*(1-D$23)*Assumptions!$D$11)*Calc_Deutsche!$B$16+Calc_Deutsche!$B$8*(1+Assumptions!$D$13)-Calc_Deutsche!$B$10*(1+Assumptions!$D$12))*(1-Calc_Deutsche!$B$21))/2) -> 0.085939405 | E25: =(((Calc_Deutsche!$B$20+$A25*(1-E$23)*Assumptions!$D$11)*Calc_Deutsche!$B$16+Calc_Deutsche!$B$8*(1+Assumptions!$D$13)-Calc_Deutsche!$B$10*(1+Assumptions!$D$12))*(1-Calc_Deutsche!$B$21))/(Calc_Deutsche!$B$17+(((Calc_Deutsche!$B$20+$A25*(1-E$23)*Assumptions!$D$11)*Calc_Deutsche!$B$16+Calc_Deutsche!$B$8*(1+Assumptions!$D$13)-Calc_Deutsche!$B$10*(1+Assumptions!$D$12))*(1-Calc_Deutsche!$B$21))/2) -> 0.087830083 | F25: =(((Calc_Deutsche!$B$20+$A25*(1-F$23)*Assumptions!$D$11)*Calc_Deutsche!$B$16+Calc_Deutsche!$B$8*(1+Assumptions!$D$13)-Calc_Deutsche!$B$10*(1+Assumptions!$D$12))*(1-Calc_Deutsche!$B$21))/(Calc_Deutsche!$B$17+(((Calc_Deutsche!$B$20+$A25*(1-F$23)*Assumptions!$D$11)*Calc_Deutsche!$B$16+Calc_Deutsche!$B$8*(1+Assumptions!$D$13)-Calc_Deutsche!$B$10*(1+Assumptions!$D$12))*(1-Calc_Deutsche!$B$21))/2) -> 0.08971703 | G25: =(((Calc_Deutsche!$B$20+$A25*(1-G$23)*Assumptions!$D$11)*Calc_Deutsche!$B$16+Calc_Deutsche!$B$8*(1+Assumptions!$D$13)-Calc_Deutsche!$B$10*(1+Assumptions!$D$12))*(1-Calc_Deutsche!$B$21))/(Calc_Deutsche!$B$17+(((Calc_Deutsche!$B$20+$A25*(1-G$23)*Assumptions!$D$11)*Calc_Deutsche!$B$16+Calc_Deutsche!$B$8*(1+Assumptions!$D$13)-Calc_Deutsche!$B$10*(1+Assumptions!$D$12))*(1-Calc_Deutsche!$B$21))/2) -> 0.091600257 | H25: =(((Calc_Deutsche!$B$20+$A25*(1-H$23)*Assumptions!$D$11)*Calc_Deutsche!$B$16+Calc_Deutsche!$B$8*(1+Assumptions!$D$13)-Calc_Deutsche!$B$10*(1+Assumptions!$D$12))*(1-Calc_Deutsche!$B$21))/(Calc_Deutsche!$B$17+(((Calc_Deutsche!$B$20+$A25*(1-H$23)*Assumptions!$D$11)*Calc_Deutsche!$B$16+Calc_Deutsche!$B$8*(1+Assumptions!$D$13)-Calc_Deutsche!$B$10*(1+Assumptions!$D$12))*(1-Calc_Deutsche!$B$21))/2) -> 0.093479774
A26: 0 | B26: =(((Calc_Deutsche!$B$20+$A26*(1-B$23)*Assumptions!$D$11)*Calc_Deutsche!$B$16+Calc_Deutsche!$B$8*(1+Assumptions!$D$13)-Calc_Deutsche!$B$10*(1+Assumptions!$D$12))*(1-Calc_Deutsche!$B$21))/(Calc_Deutsche!$B$17+(((Calc_Deutsche!$B$20+$A26*(1-B$23)*Assumptions!$D$11)*Calc_Deutsche!$B$16+Calc_Deutsche!$B$8*(1+Assumptions!$D$13)-Calc_Deutsche!$B$10*(1+Assumptions!$D$12))*(1-Calc_Deutsche!$B$21))/2) -> 0.097227723 | C26: =(((Calc_Deutsche!$B$20+$A26*(1-C$23)*Assumptions!$D$11)*Calc_Deutsche!$B$16+Calc_Deutsche!$B$8*(1+Assumptions!$D$13)-Calc_Deutsche!$B$10*(1+Assumptions!$D$12))*(1-Calc_Deutsche!$B$21))/(Calc_Deutsche!$B$17+(((Calc_Deutsche!$B$20+$A26*(1-C$23)*Assumptions!$D$11)*Calc_Deutsche!$B$16+Calc_Deutsche!$B$8*(1+Assumptions!$D$13)-Calc_Deutsche!$B$10*(1+Assumptions!$D$12))*(1-Calc_Deutsche!$B$21))/2) -> 0.097227723 | D26: =(((Calc_Deutsche!$B$20+$A26*(1-D$23)*Assumptions!$D$11)*Calc_Deutsche!$B$16+Calc_Deutsche!$B$8*(1+Assumptions!$D$13)-Calc_Deutsche!$B$10*(1+Assumptions!$D$12))*(1-Calc_Deutsche!$B$21))/(Calc_Deutsche!$B$17+(((Calc_Deutsche!$B$20+$A26*(1-D$23)*Assumptions!$D$11)*Calc_Deutsche!$B$16+Calc_Deutsche!$B$8*(1+Assumptions!$D$13)-Calc_Deutsche!$B$10*(1+Assumptions!$D$12))*(1-Calc_Deutsche!$B$21))/2) -> 0.097227723 | E26: =(((Calc_Deutsche!$B$20+$A26*(1-E$23)*Assumptions!$D$11)*Calc_Deutsche!$B$16+Calc_Deutsche!$B$8*(1+Assumptions!$D$13)-Calc_Deutsche!$B$10*(1+Assumptions!$D$12))*(1-Calc_Deutsche!$B$21))/(Calc_Deutsche!$B$17+(((Calc_Deutsche!$B$20+$A26*(1-E$23)*Assumptions!$D$11)*Calc_Deutsche!$B$16+Calc_Deutsche!$B$8*(1+Assumptions!$D$13)-Calc_Deutsche!$B$10*(1+Assumptions!$D$12))*(1-Calc_Deutsche!$B$21))/2) -> 0.097227723 | F26: =(((Calc_Deutsche!$B$20+$A26*(1-F$23)*Assumptions!$D$11)*Calc_Deutsche!$B$16+Calc_Deutsche!$B$8*(1+Assumptions!$D$13)-Calc_Deutsche!$B$10*(1+Assumptions!$D$12))*(1-Calc_Deutsche!$B$21))/(Calc_Deutsche!$B$17+(((Calc_Deutsche!$B$20+$A26*(1-F$23)*Assumptions!$D$11)*Calc_Deutsche!$B$16+Calc_Deutsche!$B$8*(1+Assumptions!$D$13)-Calc_Deutsche!$B$10*(1+Assumptions!$D$12))*(1-Calc_Deutsche!$B$21))/2) -> 0.097227723 | G26: =(((Calc_Deutsche!$B$20+$A26*(1-G$23)*Assumptions!$D$11)*Calc_Deutsche!$B$16+Calc_Deutsche!$B$8*(1+Assumptions!$D$13)-Calc_Deutsche!$B$10*(1+Assumptions!$D$12))*(1-Calc_Deutsche!$B$21))/(Calc_Deutsche!$B$17+(((Calc_Deutsche!$B$20+$A26*(1-G$23)*Assumptions!$D$11)*Calc_Deutsche!$B$16+Calc_Deutsche!$B$8*(1+Assumptions!$D$13)-Calc_Deutsche!$B$10*(1+Assumptions!$D$12))*(1-Calc_Deutsche!$B$21))/2) -> 0.097227723 | H26: =(((Calc_Deutsche!$B$20+$A26*(1-H$23)*Assumptions!$D$11)*Calc_Deutsche!$B$16+Calc_Deutsche!$B$8*(1+Assumptions!$D$13)-Calc_Deutsche!$B$10*(1+Assumptions!$D$12))*(1-Calc_Deutsche!$B$21))/(Calc_Deutsche!$B$17+(((Calc_Deutsche!$B$20+$A26*(1-H$23)*Assumptions!$D$11)*Calc_Deutsche!$B$16+Calc_Deutsche!$B$8*(1+Assumptions!$D$13)-Calc_Deutsche!$B$10*(1+Assumptions!$D$12))*(1-Calc_Deutsche!$B$21))/2) -> 0.097227723
A27: 0.0025 | B27: =(((Calc_Deutsche!$B$20+$A27*(1-B$23)*Assumptions!$D$11)*Calc_Deutsche!$B$16+Calc_Deutsche!$B$8*(1+Assumptions!$D$13)-Calc_Deutsche!$B$10*(1+Assumptions!$D$12))*(1-Calc_Deutsche!$B$21))/(Calc_Deutsche!$B$17+(((Calc_Deutsche!$B$20+$A27*(1-B$23)*Assumptions!$D$11)*Calc_Deutsche!$B$16+Calc_Deutsche!$B$8*(1+Assumptions!$D$13)-Calc_Deutsche!$B$10*(1+Assumptions!$D$12))*(1-Calc_Deutsche!$B$21))/2) -> 0.11207331 | C27: =(((Calc_Deutsche!$B$20+$A27*(1-C$23)*Assumptions!$D$11)*Calc_Deutsche!$B$16+Calc_Deutsche!$B$8*(1+Assumptions!$D$13)-Calc_Deutsche!$B$10*(1+Assumptions!$D$12))*(1-Calc_Deutsche!$B$21))/(Calc_Deutsche!$B$17+(((Calc_Deutsche!$B$20+$A27*(1-C$23)*Assumptions!$D$11)*Calc_Deutsche!$B$16+Calc_Deutsche!$B$8*(1+Assumptions!$D$13)-Calc_Deutsche!$B$10*(1+Assumptions!$D$12))*(1-Calc_Deutsche!$B$21))/2) -> 0.11023029 | D27: =(((Calc_Deutsche!$B$20+$A27*(1-D$23)*Assumptions!$D$11)*Calc_Deutsche!$B$16+Calc_Deutsche!$B$8*(1+Assumptions!$D$13)-Calc_Deutsche!$B$10*(1+Assumptions!$D$12))*(1-Calc_Deutsche!$B$21))/(Calc_Deutsche!$B$17+(((Calc_Deutsche!$B$20+$A27*(1-D$23)*Assumptions!$D$11)*Calc_Deutsche!$B$16+Calc_Deutsche!$B$8*(1+Assumptions!$D$13)-Calc_Deutsche!$B$10*(1+Assumptions!$D$12))*(1-Calc_Deutsche!$B$21))/2) -> 0.10838367 | E27: =(((Calc_Deutsche!$B$20+$A27*(1-E$23)*Assumptions!$D$11)*Calc_Deutsche!$B$16+Calc_Deutsche!$B$8*(1+Assumptions!$D$13)-Calc_Deutsche!$B$10*(1+Assumptions!$D$12))*(1-Calc_Deutsche!$B$21))/(Calc_Deutsche!$B$17+(((Calc_Deutsche!$B$20+$A27*(1-E$23)*Assumptions!$D$11)*Calc_Deutsche!$B$16+Calc_Deutsche!$B$8*(1+Assumptions!$D$13)-Calc_Deutsche!$B$10*(1+Assumptions!$D$12))*(1-Calc_Deutsche!$B$21))/2) -> 0.10653344 | F27: =(((Calc_Deutsche!$B$20+$A27*(1-F$23)*Assumptions!$D$11)*Calc_Deutsche!$B$16+Calc_Deutsche!$B$8*(1+Assumptions!$D$13)-Calc_Deutsche!$B$10*(1+Assumptions!$D$12))*(1-Calc_Deutsche!$B$21))/(Calc_Deutsche!$B$17+(((Calc_Deutsche!$B$20+$A27*(1-F$23)*Assumptions!$D$11)*Calc_Deutsche!$B$16+Calc_Deutsche!$B$8*(1+Assumptions!$D$13)-Calc_Deutsche!$B$10*(1+Assumptions!$D$12))*(1-Calc_Deutsche!$B$21))/2) -> 0.10467959 | G27: =(((Calc_Deutsche!$B$20+$A27*(1-G$23)*Assumptions!$D$11)*Calc_Deutsche!$B$16+Calc_Deutsche!$B$8*(1+Assumptions!$D$13)-Calc_Deutsche!$B$10*(1+Assumptions!$D$12))*(1-Calc_Deutsche!$B$21))/(Calc_Deutsche!$B$17+(((Calc_Deutsche!$B$20+$A27*(1-G$23)*Assumptions!$D$11)*Calc_Deutsche!$B$16+Calc_Deutsche!$B$8*(1+Assumptions!$D$13)-Calc_Deutsche!$B$10*(1+Assumptions!$D$12))*(1-Calc_Deutsche!$B$21))/2) -> 0.1028221 | H27: =(((Calc_Deutsche!$B$20+$A27*(1-H$23)*Assumptions!$D$11)*Calc_Deutsche!$B$16+Calc_Deutsche!$B$8*(1+Assumptions!$D$13)-Calc_Deutsche!$B$10*(1+Assumptions!$D$12))*(1-Calc_Deutsche!$B$21))/(Calc_Deutsche!$B$17+(((Calc_Deutsche!$B$20+$A27*(1-H$23)*Assumptions!$D$11)*Calc_Deutsche!$B$16+Calc_Deutsche!$B$8*(1+Assumptions!$D$13)-Calc_Deutsche!$B$10*(1+Assumptions!$D$12))*(1-Calc_Deutsche!$B$21))/2) -> 0.10096097
A28: 0.005 | B28: =(((Calc_Deutsche!$B$20+$A28*(1-B$23)*Assumptions!$D$11)*Calc_Deutsche!$B$16+Calc_Deutsche!$B$8*(1+Assumptions!$D$13)-Calc_Deutsche!$B$10*(1+Assumptions!$D$12))*(1-Calc_Deutsche!$B$21))/(Calc_Deutsche!$B$17+(((Calc_Deutsche!$B$20+$A28*(1-B$23)*Assumptions!$D$11)*Calc_Deutsche!$B$16+Calc_Deutsche!$B$8*(1+Assumptions!$D$13)-Calc_Deutsche!$B$10*(1+Assumptions!$D$12))*(1-Calc_Deutsche!$B$21))/2) -> 0.12668904 | C28: =(((Calc_Deutsche!$B$20+$A28*(1-C$23)*Assumptions!$D$11)*Calc_Deutsche!$B$16+Calc_Deutsche!$B$8*(1+Assumptions!$D$13)-Calc_Deutsche!$B$10*(1+Assumptions!$D$12))*(1-Calc_Deutsche!$B$21))/(Calc_Deutsche!$B$17+(((Calc_Deutsche!$B$20+$A28*(1-C$23)*Assumptions!$D$11)*Calc_Deutsche!$B$16+Calc_Deutsche!$B$8*(1+Assumptions!$D$13)-Calc_Deutsche!$B$10*(1+Assumptions!$D$12))*(1-Calc_Deutsche!$B$21))/2) -> 0.12305636 | D28: =(((Calc_Deutsche!$B$20+$A28*(1-D$23)*Assumptions!$D$11)*Calc_Deutsche!$B$16+Calc_Deutsche!$B$8*(1+Assumptions!$D$13)-Calc_Deutsche!$B$10*(1+Assumptions!$D$12))*(1-Calc_Deutsche!$B$21))/(Calc_Deutsche!$B$17+(((Calc_Deutsche!$B$20+$A28*(1-D$23)*Assumptions!$D$11)*Calc_Deutsche!$B$16+Calc_Deutsche!$B$8*(1+Assumptions!$D$13)-Calc_Deutsche!$B$10*(1+Assumptions!$D$12))*(1-Calc_Deutsche!$B$21))/2) -> 0.11940957 | E28: =(((Calc_Deutsche!$B$20+$A28*(1-E$23)*Assumptions!$D$11)*Calc_Deutsche!$B$16+Calc_Deutsche!$B$8*(1+Assumptions!$D$13)-Calc_Deutsche!$B$10*(1+Assumptions!$D$12))*(1-Calc_Deutsche!$B$21))/(Calc_Deutsche!$B$17+(((Calc_Deutsche!$B$20+$A28*(1-E$23)*Assumptions!$D$11)*Calc_Deutsche!$B$16+Calc_Deutsche!$B$8*(1+Assumptions!$D$13)-Calc_Deutsche!$B$10*(1+Assumptions!$D$12))*(1-Calc_Deutsche!$B$21))/2) -> 0.11574858 | F28: =(((Calc_Deutsche!$B$20+$A28*(1-F$23)*Assumptions!$D$11)*Calc_Deutsche!$B$16+Calc_Deutsche!$B$8*(1+Assumptions!$D$13)-Calc_Deutsche!$B$10*(1+Assumptions!$D$12))*(1-Calc_Deutsche!$B$21))/(Calc_Deutsche!$B$17+(((Calc_Deutsche!$B$20+$A28*(1-F$23)*Assumptions!$D$11)*Calc_Deutsche!$B$16+Calc_Deutsche!$B$8*(1+Assumptions!$D$13)-Calc_Deutsche!$B$10*(1+Assumptions!$D$12))*(1-Calc_Deutsche!$B$21))/2) -> 0.11207331 | G28: =(((Calc_Deutsche!$B$20+$A28*(1-G$23)*Assumptions!$D$11)*Calc_Deutsche!$B$16+Calc_Deutsche!$B$8*(1+Assumptions!$D$13)-Calc_Deutsche!$B$10*(1+Assumptions!$D$12))*(1-Calc_Deutsche!$B$21))/(Calc_Deutsche!$B$17+(((Calc_Deutsche!$B$20+$A28*(1-G$23)*Assumptions!$D$11)*Calc_Deutsche!$B$16+Calc_Deutsche!$B$8*(1+Assumptions!$D$13)-Calc_Deutsche!$B$10*(1+Assumptions!$D$12))*(1-Calc_Deutsche!$B$21))/2) -> 0.10838367 | H28: =(((Calc_Deutsche!$B$20+$A28*(1-H$23)*Assumptions!$D$11)*Calc_Deutsche!$B$16+Calc_Deutsche!$B$8*(1+Assumptions!$D$13)-Calc_Deutsche!$B$10*(1+Assumptions!$D$12))*(1-Calc_Deutsche!$B$21))/(Calc_Deutsche!$B$17+(((Calc_Deutsche!$B$20+$A28*(1-H$23)*Assumptions!$D$11)*Calc_Deutsche!$B$16+Calc_Deutsche!$B$8*(1+Assumptions!$D$13)-Calc_Deutsche!$B$10*(1+Assumptions!$D$12))*(1-Calc_Deutsche!$B$21))/2) -> 0.10467959

Sheet Scenarios
A1: Scenario Comparison - FY2025E by Bank
A2: Bear: −25bps rate change | Base: 0bps | Bull: +25bps. Fees, OpEx, tax, β, lag per Assumptions.
B3: Bear | C3: Base | D3: Bull
A4: ΔRate applied | B4: -0.0025 | C4: 0 | D4: 0.0025
A6: Barclays (GBP, bn)
A7: Net Income | B7: =((Calc_Barclays!$B$20+B$4*(1-Assumptions!$B$10)*Assumptions!$B$11)*Calc_Barclays!$B$16+Calc_Barclays!$B$8*(1+Assumptions!$B$13)-Calc_Barclays!$B$10*(1+Assumptions!$B$12))*(1-Assumptions!$B$14) -> 6.8497218 | C7: =((Calc_Barclays!$B$20+C$4*(1-Assumptions!$B$10)*Assumptions!$B$11)*Calc_Barclays!$B$16+Calc_Barclays!$B$8*(1+Assumptions!$B$13)-Calc_Barclays!$B$10*(1+Assumptions!$B$12))*(1-Assumptions!$B$14) -> 7.965828 | D7: =((Calc_Barclays!$B$20+D$4*(1-Assumptions!$B$10)*Assumptions!$B$11)*Calc_Barclays!$B$16+Calc_Barclays!$B$8*(1+Assumptions!$B$13)-Calc_Barclays!$B$10*(1+Assumptions!$B$12))*(1-Assumptions!$B$14) -> 9.0819342
A8: ROE | B8: =B7/(Calc_Barclays!$B$17+B7/2) -> 0.09103121 | C8: =C7/(Calc_Barclays!$B$17+C7/2) -> 0.10508465 | D8: =D7/(Calc_Barclays!$B$17+D7/2) -> 0.11893269
A9: NIM | B9: =Calc_Barclays!$B$20+B$4*(1-Assumptions!$B$10)*Assumptions!$B$11 -> 0.0075781053 | C9: =Calc_Barclays!$B$20+C$4*(1-Assumptions!$B$10)*Assumptions!$B$11 -> 0.0085206053 | D9: =Calc_Barclays!$B$20+D$4*(1-Assumptions!$B$10)*Assumptions!$B$11 -> 0.0094631053
A10: Cost to Income | B10: =(Calc_Barclays!$B$10*(1+Assumptions!$B$12))/((Calc_Barclays!$B$20+B$4*(1-Assumptions!$B$10)*Assumptions!$B$11)*Calc_Barclays!$B$16+Calc_Barclays!$B$8*(1+Assumptions!$B$13)) -> 0.64964279 | C10: =(Calc_Barclays!$B$10*(1+Assumptions!$B$12))/((Calc_Barclays!$B$20+C$4*(1-Assumptions!$B$10)*Assumptions!$B$11)*Calc_Barclays!$B$16+Calc_Barclays!$B$8*(1+Assumptions!$B$13)) -> 0.61455894 | D10: =(Calc_Barclays!$B$10*(1+Assumptions!$B$12))/((Calc_Barclays!$B$20+D$4*(1-Assumptions!$B$10)*Assumptions!$B$11)*Calc_Barclays!$B$16+Calc_Barclays!$B$8*(1+Assumptions!$B$13)) -> 0.58307033
A12: BNP Paribas (EUR, bn)
A13: Net Income | B13: =((Calc_BNP!$B$20+B$4*(1-Assumptions!$C$10)*Assumptions!$C$11)*Calc_BNP!$B$16+Calc_BNP!$B$8*(1+Assumptions!$C$13)-Calc_BNP!$B$10*(1+Assumptions!$C$12))*(1-Assumptions!$C$14) -> 11.708767 | C13: =((Calc_BNP!$B$20+C$4*(1-Assumptions!$C$10)*Assumptions!$C$11)*Calc_BNP!$B$16+Calc_BNP!$B$8*(1+Assumptions!$C$13)-Calc_BNP!$B$10*(1+Assumptions!$C$12))*(1-Assumptions!$C$14) -> 13.557707 | D13: =((Calc_BNP!$B$20+D$4*(1-Assumptions!$C$10)*Assumptions!$C$11)*Calc_BNP!$B$16+Calc_BNP!$B$8*(1+Assumptions!$C$13)-Calc_BNP!$B$10*(1+Assumptions!$C$12))*(1-Assumptions!$C$14) -> 15.406647
A14: ROE | B14: =B13/(Calc_BNP!$B$17+B13/2) -> 0.087384479 | C14: =C13/(Calc_BNP!$B$17+C13/2) -> 0.1004901 | D14: =D13/(Calc_BNP!$B$17+D13/2) -> 0.11341733
A15: NIM | B15: =Calc_BNP!$B$20+B$4*(1-Assumptions!$C$10)*Assumptions!$C$11 -> 0.0062879904 | C15: =Calc_BNP!$B$20+C$4*(1-Assumptions!$C$10)*Assumptions!$C$11 -> 0.0072179904 | D15: =Calc_BNP!$B$20+D$4*(1-Assumptions!$C$10)*Assumptions!$C$11 -> 0.0081479904
A16: Cost to Income | B16: =(Calc_BNP!$B$10*(1+Assumptions!$C$12))/((Calc_BNP!$B$20+B$4*(1-Assumptions!$C$10)*Assumptions!$C$11)*Calc_BNP!$B$16+Calc_BNP!$B$8*(1+Assumptions!$C$13)) -> 0.7521786 | C16: =(Calc_BNP!$B$10*(1+Assumptions!$C$12))/((Calc_BNP!$B$20+C$4*(1-Assumptions!$C$10)*Assumptions!$C$11)*Calc_BNP!$B$16+Calc_BNP!$B$8*(1+Assumptions!$C$13)) -> 0.72385164 | D16: =(Calc_BNP!$B$10*(1+Assumptions!$C$12))/((Calc_BNP!$B$20+D$4*(1-Assumptions!$C$10)*Assumptions!$C$11)*Calc_BNP!$B$16+Calc_BNP!$B$8*(1+Assumptions!$C$13)) -> 0.69758082
A18: Deutsche Bank (EUR, bn)
A19: Net Income | B19: =((Calc_Deutsche!$B$20+B$4*(1-Assumptions!$D$10)*Assumptions!$D$11)*Calc_Deutsche!$B$16+Calc_Deutsche!$B$8*(1+Assumptions!$D$13)-Calc_Deutsche!$B$10*(1+Assumptions!$D$12))*(1-Calc_Deutsche!$B$21) -> 6.8599689 | C19: =((Calc_Deutsche!$B$20+C$4*(1-Assumptions!$D$10)*Assumptions!$D$11)*Calc_Deutsche!$B$16+Calc_Deutsche!$B$8*(1+Assumptions!$D$13)-Calc_Deutsche!$B$10*(1+Assumptions!$D$12))*(1-Calc_Deutsche!$B$21) -> 7.9534949 | D19: =((Calc_Deutsche!$B$20+D$4*(1-Assumptions!$D$10)*Assumptions!$D$11)*Calc_Deutsche!$B$16+Calc_Deutsche!$B$8*(1+Assumptions!$D$13)-Calc_Deutsche!$B$10*(1+Assumptions!$D$12))*(1-Calc_Deutsche!$B$21) -> 9.0470208
A20: ROE | B20: =B19/(Calc_Deutsche!$B$17+B19/2) -> 0.084424168 | C20: =C19/(Calc_Deutsche!$B$17+C19/2) -> 0.097227723 | D20: =D19/(Calc_Deutsche!$B$17+D19/2) -> 0.10986126
A21: NIM | B21: =Calc_Deutsche!$B$20+B$4*(1-Assumptions!$D$10)*Assumptions!$D$11 -> 0.0082276879 | C21: =Calc_Deutsche!$B$20+C$4*(1-Assumptions!$D$10)*Assumptions!$D$11 -> 0.0094176879 | D21: =Calc_Deutsche!$B$20+D$4*(1-Assumptions!$D$10)*Assumptions!$D$11 -> 0.010607688
A22: Cost to Income | B22: =(Calc_Deutsche!$B$10*(1+Assumptions!$D$12))/((Calc_Deutsche!$B$20+B$4*(1-Assumptions!$D$10)*Assumptions!$D$11)*Calc_Deutsche!$B$16+Calc_Deutsche!$B$8*(1+Assumptions!$D$13)) -> 0.63963153 | C22: =(Calc_Deutsche!$B$10*(1+Assumptions!$D$12))/((Calc_Deutsche!$B$20+C$4*(1-Assumptions!$D$10)*Assumptions!$D$11)*Calc_Deutsche!$B$16+Calc_Deutsche!$B$8*(1+Assumptions!$D$13)) -> 0.60488385 | D22: =(Calc_Deutsche!$B$10*(1+Assumptions!$D$12))/((Calc_Deutsche!$B$20+D$4*(1-Assumptions!$D$10)*Assumptions!$D$11)*Calc_Deutsche!$B$16+Calc_Deutsche!$B$8*(1+Assumptions!$D$13)) -> 0.57371696

Sheet Chartbook
A1: EMEA Banks - Chartbook
A2: Source: Company annual reports, Yahoo Finance (yfinance)
A4: Chart 1 data: FY2025E Net Income by scenario
A5: Bank | B5: Bear | C5: Base | D5: Bull
A6: Barclays | B6: =Scenarios!B7 -> 6.8497218 | C6: =Scenarios!C7 -> 7.965828 | D6: =Scenarios!D7 -> 9.0819342
A7: BNP Paribas | B7: =Scenarios!B13 -> 11.708767 | C7: =Scenarios!C13 -> 13.557707 | D7: =Scenarios!D13 -> 15.406647
A8: Deutsche Bank | B8: =Scenarios!B19 -> 6.8599689 | C8: =Scenarios!C19 -> 7.9534949 | D8: =Scenarios!D19 -> 9.0470208
A10: Chart 2 data: Historical ROE (%)
A11: Year | B11: Barclays | C11: BNP Paribas | D11: Deutsche Bank | E11: 10% Target
A12: 2022 | B12: ='ratios_summary'!D2 -> 8.6804 | C12: ='ratios_summary'!D5 -> 8.1229 | D12: ='ratios_summary'!D8 -> 7.8328 | E12: 10
A13: 2023 | B13: ='ratios_summary'!D3 -> 7.3858 | C13: ='ratios_summary'!D6 -> 8.8693 | D13: ='ratios_summary'!D9 -> 6.5322 | E13: 10
A14: 2024 | B14: ='ratios_summary'!D4 -> 8.7816 | C14: ='ratios_summary'!D7 -> 9.1215 | D14: ='ratios_summary'!D10 -> 4.325 | E14: 10
A16: Chart 3 data: Historical NIM (%)
A17: Year | B17: Barclays | C17: BNP Paribas | D17: Deutsche Bank
A18: 2022 | B18: ='ratios_summary'!C2 -> 0.6984 | C18: ='ratios_summary'!C5 -> 0.7858 | D18: ='ratios_summary'!C8 -> 1.0211
A19: 2023 | B19: ='ratios_summary'!C3 -> 0.8602 | C19: ='ratios_summary'!C6 -> 0.7354 | D19: ='ratios_summary'!C9 -> 1.0365 | F19: Source: Company annual reports, Yahoo Finance (yfinance)
A20: 2024 | B20: ='ratios_summary'!C4 -> 0.8521 | C20: ='ratios_summary'!C7 -> 0.7218 | D20: ='ratios_summary'!C10 -> 0.9418
A22: Chart 4 data: FY2024 Cost-to-Income (%)
A23: Bank | B23: C/I % | C23: 70% Threshold
A24: Barclays | B24: ='ratios_summary'!F4 -> 60.8616 | C24: 70
A25: BNP Paribas | B25: ='ratios_summary'!F7 -> 71.9645 | C25: 70
A26: Deutsche Bank | B26: ='ratios_summary'!F10 -> 59.9727 | C26: 70
F35: Source: Company annual reports, Yahoo Finance (yfinance)
F51: Source: Company annual reports, Yahoo Finance (yfinance)
F67: Source: Company annual reports, Yahoo Finance (yfinance)

Sheet ratios_summary
A1: Bank | B1: Year | C1: NIM (%) | D1: ROE (%) | E1: ROA (%) | F1: Cost to Income (%) | G1: Net Income (bn)
A2: Barclays | B2: 2022 | C2: 0.6984 | D2: 8.6804 | E2: 0.3916 | F2: 60.2574 | G2: 5.928
A3: Barclays | B3: 2023 | C3: 0.8602 | D3: 7.3858 | E3: 0.3559 | F3: 63.3431 | G3: 5.259
A4: Barclays | B4: 2024 | C4: 0.8521 | D4: 8.7816 | E4: 0.4154 | F4: 60.8616 | G4: 6.307
A5: BNP Paribas | B5: 2022 | C5: 0.7858 | D5: 8.1229 | E5: 0.3697 | F5: 72.8726 | G5: 9.848
A6: BNP Paribas | B6: 2023 | C6: 0.7354 | D6: 8.8693 | E6: 0.4235 | F6: 75.028 | G6: 10.975
A7: BNP Paribas | B7: 2024 | C7: 0.7218 | D7: 9.1215 | E7: 0.4321 | F7: 71.9645 | G7: 11.688
A8: Deutsche Bank | B8: 2022 | C8: 1.0211 | D8: 7.8328 | E8: 0.4133 | F8: 66.1427 | G8: 5.525
A9: Deutsche Bank | B9: 2023 | C9: 1.0365 | D9: 6.5322 | E9: 0.3636 | F9: 63.0684 | G9: 4.772
A10: Deutsche Bank | B10: 2024 | C10: 0.9418 | D10: 4.325 | E10: 0.2427 | F10: 59.9727 | G10: 3.366

Sheet sensitivity_results
A1: Bank | B1: Scenario | C1: NIM (%) | D1: Net Income (bn) | E1: ROE (%) | F1: Income Change (bn) | G1: Income Change (%)
A2: Barclays | B2: Bear Case (-25bps) | C2: 0.6021 | D2: 2.511 | E2: 3.5 | F2: -3.796 | G2: -60.2
A3: Barclays | B3: Base Case | C3: 0.8521 | D3: 6.307 | E3: 8.78 | F3: 0 | G3: 0
A4: Barclays | B4: Bull Case (+25bps) | C4: 1.1021 | D4: 10.103 | E4: 14.07 | F4: 3.796 | G4: 60.2
A5: BNP Paribas | B5: Bear Case (-25bps) | C5: 0.4718 | D5: 4.926 | E5: 3.84 | F5: -6.762 | G5: -57.9
A6: BNP Paribas | B6: Base Case | C6: 0.7218 | D6: 11.688 | E6: 9.12 | F6: 0 | G6: 0
A7: BNP Paribas | B7: Bull Case (+25bps) | C7: 0.9718 | D7: 18.45 | E7: 14.4 | F7: 6.762 | G7: 57.9
A8: Deutsche Bank | B8: Bear Case (-25bps) | C8: 0.6918 | D8: -0.102 | E8: -0.13 | F8: -3.468 | G8: -103
A9: Deutsche Bank | B9: Base Case | C9: 0.9418 | D9: 3.366 | E9: 4.32 | F9: 0 | G9: 0
A10: Deutsche Bank | B10: Bull Case (+25bps) | C10: 1.1918 | D10: 6.834 | E10: 8.78 | F10: 3.468 | G10: 103

Sheet income_Barclays
A1: Line Item | B1: FY2025 | C1: FY2024 | D1: FY2023 | E1: FY2022 | F1: FY2021
A2: Tax Effect Of Unusual Items | B2: -1.978897e+08 | C2: -91619142 | D2: -160176000 | E2: -255596000
A3: Tax Rate For Calcs | B3: 0.210745 | C3: 0.216083 | D3: 0.188 | E3: 0.148
A4: Total Unusual Items | B4: -939000000 | C4: -424000000 | D4: -852000000 | E4: -1727000000
A5: Total Unusual Items Excluding Goodwill | B5: -939000000 | C5: -424000000 | D5: -852000000 | E5: -1727000000
A6: Net Income From Continuing Operation Net Minority Interest | B6: 7172000000 | C6: 6307000000 | D6: 5259000000 | E6: 5928000000
A7: Reconciled Depreciation | B7: 1756000000 | C7: 1700000000 | D7: 1784000000 | E7: 1723000000
A8: Net Interest Income | B8: 14501000000 | C8: 12936000000 | D8: 12709000000 | E8: 10572000000
A9: Interest Expense | B9: 21688000000 | C9: 25390000000 | D9: 22366000000 | E9: 8524000000
A10: Interest Income | B10: 36189000000 | C10: 38326000000 | D10: 35075000000 | E10: 19096000000
A11: Normalized Income | B11: 7.9131103e+09 | C11: 6.6393809e+09 | D11: 5950824000 | E11: 7399404000
A12: Net Income From Continuing And Discontinued Operation | B12: 7172000000 | C12: 6307000000 | D12: 5259000000 | E12: 5928000000
A13: Diluted Average Shares | B13: 14604000000 | C13: 15271000000 | D13: 15895000000 | E13: 16867000000
... A22: Net Income Including Noncontrolling Interests | B22: 7213000000 | C22: 6356000000 | D22: 5323000000 | E22: 5973000000
A23: Net Income Extraordinary | F23: -804000000
A24: Net Income Continuous Operations | B24: 7213000000 | C24: 6356000000 | D24: 5323000000 | E24: 5973000000
A25: Tax Provision | B25: 1926000000 | C25: 1752000000 | D25: 1234000000 | E25: 1039000000
A26: Pretax Income | B26: 9139000000 | C26: 8108000000 | D26: 6557000000 | E26: 7012000000
A27: Special Income Charges | B27: -939000000 | C27: -424000000 | D27: -852000000 | E27: -1727000000
A28: Other Special Charges | B28: 720000000 | C28: 502000000 | D28: 37000000 | E28: 1671000000
A29: Impairment Of Capital Assets | B29: 20000000 | C29: 34000000 | D29: 363000000 | E29: 63000000
A30: Restructuring And Mergern Acquisition | B30: 199000000 | C30: -112000000 | D30: 452000000 | E30: -7000000
A31: Gain On Sale Of Security | B31: 10000000 | C31: 433000000 | D31: 61000000 | E31: -391000000
A32: Operating Expense | B32: 16849000000 | C32: 15964000000 | D32: 16079000000 | E32: 15077000000
A33: Other Operating Expenses | B33: 28000000 | C33: 38000000 | D33: 180000000 | E33: 176000000
A34: Depreciation And Amortization In Income Statement | B34: 1756000000 | C34: 1700000000 | D34: 1784000000 | E34: 1723000000
A35: Depreciation Income Statement | B35: 1756000000 | C35: 1700000000 | D35: 1784000000 | E35: 1723000000
... A41: Operating Revenue | B41: 29140000000 | C41: 26230000000 | D41: 25384000000 | E41: 25021000000

Sheet income_BNP_Paribas
A1: Line Item | B1: FY2025 | C1: FY2024 | D1: FY2023 | E1: FY2022 | F1: FY2021
A2: Tax Effect Of Unusual Items | B2: 14245000 | C2: 19912000 | D2: -7325000 | E2: 28512000
A3: Tax Rate For Calcs | B3: 0.259 | C3: 0.262 | D3: 0.293 | E3: 0.297
A4: Total Unusual Items | B4: 55000000 | C4: 76000000 | D4: -25000000 | E4: 96000000
A5: Total Unusual Items Excluding Goodwill | B5: 55000000 | C5: 76000000 | D5: -25000000 | E5: 96000000
A6: Net Income From Continuing Operation Net Minority Interest | B6: 12225000000 | C6: 11688000000 | D6: 8028000000 | E6: 9161000000
A7: Reconciled Depreciation | B7: 8055000000 | C7: 7272000000 | D7: 6245000000 | E7: 6465000000
A8: Net Interest Income | B8: 21203000000 | C8: 19524000000 | D8: 19058000000 | E8: 20933000000
A9: Interest Expense | B9: 50329000000 | C9: 63496000000 | D9: 60484000000 | E9: 20149000000
A10: Interest Income | B10: 71532000000 | C10: 83020000000 | D10: 79542000000 | E10: 41082000000
A11: Normalized Income | B11: 12184245000 | C11: 11631912000 | D11: 8045675000 | E11: 9121512000
A12: Net Income From Continuing And Discontinued Operation | B12: 12225000000 | C12: 11688000000 | D12: 10975000000 | E12: 9848000000
A13: Diluted Average Shares | B13: 1188046647 | C13: 1133302357 | D13: 1200367337 | E13: 1232991607
... A22: Net Income Including Noncontrolling Interests | B22: 12858000000 | C22: 12187000000 | D22: 11406000000 | E22: 10248000000
A23: Net Income Discontinuous Operations | C23: 0 | D23: 2947000000 | E23: 687000000 | F23: 720000000
A24: Net Income Continuous Operations | B24: 12858000000 | C24: 12187000000 | D24: 8459000000 | E24: 9561000000
A25: Tax Provision | B25: 4207000000 | C25: 4001000000 | D25: 3266000000 | E25: 3653000000
A26: Pretax Income | B26: 17065000000 | C26: 16188000000 | D26: 11725000000 | E26: 13214000000
A27: Special Income Charges | B27: -12000000 | C27: 16000000 | D27: -123000000 | E27: -52000000
A28: Other Special Charges | B28: 56000000 | C28: 191000000 | D28: 104000000 | E28: 253000000
A29: Write Off | E29: 17000000 | F29: -12000000
A30: Impairment Of Capital Assets | B30: 4000000 | C30: 34000000 | D30: 19000000 | E30: 20000000
A31: Restructuring And Mergern Acquisition | B31: -48000000 | C31: -241000000 | D31: 0 | E31: -249000000
A32: Gain On Sale Of Security | B32: -1253000000 | C32: 33000000 | D32: -3410000000 | E32: 11439000000
A33: Operating Expense | B33: 49005000000 | C33: 47403000000 | D33: 44818000000 | E33: 41885000000
A34: Other Operating Expenses | B34: 11086000000 | C34: 11428000000 | D34: 12999000000 | E34: 12702000000
A35: Depreciation And Amortization In Income Statement | B35: 2367000000 | C35: 2356000000 | D35: 2224000000 | E35: 2284000000
A36: Depreciation Income Statement | B36: 2367000000 | C36: 2356000000 | D36: 2224000000 | E36: 2284000000
A37: Selling General And Administration | E37: 10447000000 | F37: 9679000000
A38: General And Administrative Expense | E38: 10447000000 | F38: 9679000000
A39: Insurance And Claims | B39: -288000000 | C39: -253000000 | D39: -283000000 | E39: -343000000
A40: Rent And Landing Fees | B40: 16703000000 | C40: 15729000000 | D40: 12103000000 | E40: 10365000000
A41: Total Revenue | B41: 68804000000 | C41: 65870000000 | D41: 59735000000 | E41: 57477000000
A42: Operating Revenue | B42: 68804000000 | C42: 65870000000 | D42: 59735000000 | E42: 57477000000

Sheet income_Deutsche_Bank
A1: Line Item | B1: FY2025 | C1: FY2024 | D1: FY2023 | E1: FY2022
A2: Tax Effect Of Unusual Items | B2: -96690577 | C2: -8.5468758e+08 | D2: -149660000 | E2: -10350000
A3: Tax Rate For Calcs | B3: 0.266365 | C3: 0.337554 | D3: 0.14 | E3: 0.15
A4: Total Unusual Items | B4: -363000000 | C4: -2532000000 | D4: -1069000000 | E4: -69000000
A5: Total Unusual Items Excluding Goodwill | B5: -363000000 | C5: -2532000000 | D5: -1069000000 | E5: -69000000
A6: Net Income From Continuing Operation Net Minority Interest | B6: 6931000000 | C6: 3366000000 | D6: 4772000000 | E6: 5525000000
A7: Net Interest Income | B7: 15690000000 | C7: 13064000000 | D7: 13602000000 | E7: 13650000000
A8: Interest Expense | B8: 28768000000 | C8: 36292000000 | D8: 30473000000 | E8: 10649000000
A9: Interest Income | B9: 44458000000 | C9: 49356000000 | D9: 44075000000 | E9: 24299000000
A10: Normalized Income | B10: 7.1973094e+09 | C10: 5.0433124e+09 | D10: 5691340000 | E10: 5583650000
A11: Net Income From Continuing And Discontinued Operation | B11: 6931000000 | C11: 3366000000 | D11: 4772000000 | E11: 5525000000
A12: Diluted Average Shares | B12: 1939573264 | C12: 2039300000 | D12: 2104000000 | E12: 2125600000
A13: Basic Average Shares | B13: 1939573264 | C13: 1993600000 | D13: 2064100000 | E13: 2084900000
... A40: Other Non Interest Expense | B40: -50000000 | C40: -360000000 | D40: 182000000 | E40: 652000000

Sheet balance_Barclays
A1: Line Item | B1: FY2025 | C1: FY2024 | D1: FY2023 | E1: FY2022
A2: Treasury Shares Number | B2: 20000000 | C2: 19000000 | D2: 19000000 | E2: 0
A3: Ordinary Shares Number | B3: 13844768457 | C3: 14400599565 | D3: 15135554000 | E3: 15871000000
A4: Share Issued | B4: 13864768457 | C4: 14419599565 | D4: 15154554000 | E4: 15871000000
A5: Total Debt | B5: 219941000000 | C5: 185746000000 | D5: 176551000000 | E5: 183366000000
A6: Tangible Book Value | B6: 69500000000 | C6: 63546000000 | D6: 63410000000 | E6: 60053000000
A7: Invested Capital | B7: 296447000000 | C7: 256362000000 | D7: 246784000000 | E7: 250442000000
A8: Net Tangible Assets | B8: 69500000000 | C8: 63546000000 | D8: 63410000000 | E8: 60053000000
A9: Common Stock Equity | B9: 77784000000 | C9: 71821000000 | D9: 71204000000 | E9: 68292000000
A10: Total Capitalization | B10: 296447000000 | C10: 256362000000 | D10: 246784000000 | E10: 250442000000
A11: Total Equity Gross Minority Interest | B11: 78236000000 | C11: 72481000000 | D11: 71864000000 | E11: 69260000000
A12: Minority Interest | B12: 452000000 | C12: 660000000 | D12: 660000000 | E12: 968000000
A13: Stockholders Equity | B13: 77784000000 | C13: 71821000000 | D13: 71204000000 | E13: 68292000000
... A46: Cash Cash Equivalents And Federal Funds Sold | B46: 379862000000 | C46: 356691000000 | D46: 376359000000 | E46: 421808000000

Sheet balance_BNP_Paribas
A1: Line Item | B1: FY2025 | C1: FY2024 | D1: FY2023 | E1: FY2022 | F1: FY2021
A2: Treasury Shares Number | B2: 16685450 | C2: 1256198 | D2: 0 | E2: 881641
A3: Ordinary Shares Number | B3: 1100099307 | C3: 1129554473 | D3: 1147477409 | E3: 1233450005
A4: Share Issued | B4: 1116784757 | C4: 1130810671 | D4: 1147477409 | E4: 1234331646
A5: Net Debt | B5: 68658000000 | C5: 69001000000
A6: Total Debt | B6: 398488000000 | C6: 379895000000 | D6: 346845000000 | E6: 293984000000
A7: Tangible Book Value | B7: 113797000000 | C7: 118195000000 | D7: 114051000000 | E7: 112153000000
A8: Invested Capital | B8: 521130000000 | C8: 505184000000 | D8: 467529000000 | E8: 412146000000
A9: Net Tangible Assets | B9: 113797000000 | C9: 118195000000 | D9: 114051000000 | E9: 112153000000
A10: Common Stock Equity | B10: 125513000000 | C10: 128137000000 | D10: 123742000000 | E10: 121237000000
A11: Total Capitalization | B11: 521130000000 | C11: 505184000000 | D11: 467529000000 | E11: 412146000000
A12: Total Equity Gross Minority Interest | B12: 132173000000 | C12: 134141000000 | D12: 128867000000 | E12: 126010000000
A13: Minority Interest | B13: 6660000000 | C13: 6004000000 | D13: 5125000000 | E13: 4773000000
A14: Stockholders Equity | B14: 125513000000 | C14: 128137000000 | D14: 123742000000 | E14: 121237000000
A15: Other Equity Interest | B15: 6115000000 | C15: 9621000000 | D15: 10430000000 | E15: 8181000000
A16: Retained Earnings | B16: 101570000000 | C16: 98383000000 | D16: 92110000000 | E16: 86866000000
A17: Capital Stock | B17: 17828000000 | C17: 20133000000 | D17: 21202000000 | E17: 26190000000
... A31: Long Term Equity Investment | B31: 6950000000 | C31: 7862000000 | D31: 6751000000 | E31: 6073000000
A32: Investmentsin Joint Venturesat Cost | C32: 1960000000 | D32: 1784000000 | E32: 1445000000 | F32: 1022000000
A33: Investmentsin Associatesat Cost | C33: 5902000000 | D33: 4967000000 | E33: 4628000000 | F33: 5506000000
A34: Investment Properties | B34: 381000000 | C34: 524000000 | D34: 486000000 | E34: 529000000
A35: Goodwill And Other Intangible Assets | B35: 11716000000 | C35: 9942000000 | D35: 9691000000 | E35: 9084000000
A36: Other Intangible Assets | B36: 4583000000 | C36: 4392000000 | D36: 4142000000 | E36: 3790000000
A37: Goodwill | B37: 7133000000 | C37: 5550000000 | D37: 5549000000 | E37: 5294000000
A38: Net PPE | B38: 53220000000 | C38: 49790000000 | D38: 44736000000 | E38: 37939000000
A39: Accumulated Depreciation | B39: -23654000000 | C39: -22583000000 | D39: -21646000000 | E39: -21880000000
A40: Gross PPE | B40: 76874000000 | C40: 72373000000 | D40: 66382000000 | E40: 59819000000
A41: Other Properties | B41: 58709000000 | C41: 54257000000 | D41: 48058000000 | E41: 41135000000
A42: Machinery Furniture Equipment | B42: 6912000000 | C42: 7067000000 | D42: 7007000000 | E42: 7177000000
A43: Properties | B43: 11253000000 | C43: 11049000000 | D43: 11317000000 | E43: 11507000000
A44: Receivables | B44: 7527000000 | C44: 5686000000 | D44: 5400000000 | E44: 6839000000
A45: Taxes Receivable | B45: 2496000000 | C45: 2836000000 | D45: 2942000000 | E45: 1685000000
... A48: Cash Cash Equivalents And Federal Funds Sold | B48: 576860000000 | C48: 529234000000 | D48: 629892000000 | E48: 662196000000

Sheet balance_Deutsche_Bank
A1: Line Item | B1: FY2025 | C1: FY2024 | D1: FY2023 | E1: FY2022
A2: Treasury Shares Number | B2: 7705713 | C2: 49575838 | D2: 48195109 | E2: 28931618
A3: Ordinary Shares Number | B3: 1939573264 | C3: 1983625755 | D3: 2038347850 | E3: 2083441513
A4: Share Issued | B4: 1947278977 | C4: 2033201593 | D4: 2086542959 | E4: 2112373131
A5: Total Debt | B5: 164452000000 | C5: 151490000000 | D5: 144217000000 | E5: 146379000000
A6: Tangible Book Value | B6: 71080000000 | C6: 70077000000 | D6: 65727000000 | E6: 63445000000
A7: Invested Capital | B7: 238900000000 | C7: 224828000000 | D7: 212778000000 | E7: 212446000000
A8: Net Tangible Assets | B8: 71080000000 | C8: 70077000000 | D8: 65727000000 | E8: 63445000000
A9: Capital Lease Obligations | B9: 4193000000 | C9: 4488000000 | D9: 4493000000 | E9: 4470000000
A10: Common Stock Equity | B10: 78641000000 | C10: 77826000000 | D10: 73054000000 | E10: 70537000000
A11: Total Capitalization | B11: 220696000000 | C11: 214934000000 | D11: 203158000000 | E11: 207324000000
A12: Total Equity Gross Minority Interest | B12: 80203000000 | C12: 79432000000 | D12: 74817000000 | E12: 72328000000
A13: Minority Interest | B13: 1562000000 | C13: 1606000000 | D13: 1763000000 | E13: 1791000000
... A61: Cash Cash Equivalents And Federal Funds Sold | B61: 306060000000 | C61: 285979000000 | D61: 267023000000 | E61: 263580000000

Sheet bank_metrics
A1: Bank | B1: Current Price | C1: Currency | D1: Market Cap | E1: P/B Ratio | F1: P/E Ratio | G1: ROE | H1: ROA | I1: Profit Margin | J1: Total Revenue | K1: Total Assets | L1: Book Value
A2: Barclays | B2: 373.9 | C2: GBp | D2: 51501977600 | E2: 79.58706 | F2: 8.902381 | G2: 0.09571999 | H2: 0.00471 | I2: 0.26743 | J2: 26818000896 | L2: 4.698
A3: BNP Paribas | B3: 82.13 | C3: EUR | D3: 91721531392 | E3: 0.78635436 | F3: 7.9815354 | G3: 0.09656 | H3: 0.00468 | I3: 0.25502002 | J3: 47936999424 | L3: 104.444
A4: Deutsche Bank | B4: 24.76 | C4: EUR | D4: 48023834624 | E4: 0.5836594 | F4: 8.012945 | G4: 0.08302 | H4: 0.00481 | I4: 0.22222 | J4: 29727000576 | L4: 42.422

Sheet bank_prices
A1: Date | B1: Barclays | C1: BNP Paribas | D1: Deutsche Bank
A2: 45004.958 | C2: 41.828629 | D2: 8.5051107
A3: 45005 | B3: 136.2235
A4: 45005.958 | C4: 43.56353 | D4: 9.0197954
A5: 45006 | B5: 142.9967
A6: 45006.958 | C6: 43.348656 | D6: 8.8311386
A7: 45007 | B7: 142.5172
A8: 45007.958 | C8: 42.401623 | D8: 8.5499868
A9: 45008 | B9: 139.64006
A10: 45008.958 | C10: 40.165352 | D10: 7.821002
A11: 45009 | B11: 133.76595
A12: 45011.958 | C12: 41.215843 | D12: 8.3018026
A13: 45012 | B13: 136.86284
A14: 45012.958 | C14: 41.359093 | D14: 8.1708412
A15: 45013 | B15: 137.04266
A16: 45013.958 | C16: 42.473244 | D16: 8.3732338
A17: 45014 | B17: 141.87782
A18: 45014.958 | C18: 43.3964 | D18: 8.5069427
A19: 45015 | B19: 144.67503
A20: 45015.958 | C20: 43.937565 | D20: 8.5683022
A21: 45016 | B21: 145.65405
A22: 45018.958 | C22: 44.407104 | D22: 8.6681261
A23: 45019 | B23: 148.11157
A24: 45019.958 | C24: 44.836853 | D24: 8.5426588
A25: 45020 | B25: 146.35335
A26: 45020.958 | C26: 44.430977 | D26: 8.5170174
A27: 45021 | B27: 147.57211
A28: 45021.958 | C28: 45.545139 | D28: 8.6598835
A29: 45022 | B29: 151.46822
A30: 45026.958 | C30: 45.298428 | D30: 8.7597055
A31: 45027 | B31: 152.38728
A32: 45027.958 | C32: 45.417801 | D32: 8.7880955
A33: 45028 | B33: 152.90678
A34: 45028.958 | C34: 45.79184 | D34: 8.7175789
A35: 45029 | B35: 152.7869
A36: 45029.958 | C36: 47.264122 | D36: 9.1159554
A37: 45030 | B37: 157.72195
A38: 45032.958 | C38: 46.309128 | D38: 8.9135609
A39: 45033 | B39: 154.12555
A40: 45033.958 | C40: 47.280041 | D40: 9.0793228
A41: 45034 | B41: 154.80487
A42: 45034.958 | C42: 47.431244 | D42: 9.1635771
A43: 45035 | B43: 155.24443
A44: 45035.958 | C44: 46.834373 | D44: 9.0784073
A45: 45036 | B45: 154.30539
A46: 45036.958 | C46: 46.68317 | D46: 9.061923
A47: 45037 | B47: 153.08662
A48: 45039.958 | C48: 47.065166 | D48: 9.0637541
A49: 45040 | B49: 154.04562
A50: 45040.958 | C50: 45.94305 | D50: 8.7166624
A51: 45041 | B51: 151.30838
A52: 45041.958 | C52: 45.847549 | D52: 8.7532959
A53: 45042 | B53: 153.70596
A54: 45042.958 | C54: 46.746834 | D54: 8.9694262
A55: 45043 | B55: 161.87778
A56: 45043.958 | C56: 46.62746 | D56: 9.1058807
A57: 45044 | B57: 159.71996
A58: 45047.958 | C58: 45.330265 | D58: 8.8219814
A59: 45048 | B59: 154.7849
A60: 45048.958 | C60: 44.797062 | D60: 8.7597055
A61: 45049 | B61: 153.10655
A62: 45049.958 | C62: 44.518517 | D62: 8.4684792
A63: 45050 | B63: 148.09158
A64: 45050.958 | C64: 46.070381 | D64: 8.8512869
A65: 45051 | B65: 153.08662
A66: 45053.958 | C66: 46.388714 | D66: 8.8595285
A67: 45054.958 | C67: 46.492168 | D67: 8.856782
A68: 45055 | B68: 153.42627
A69: 45055.958 | C69: 46.094254 | D69: 8.8979931
A70: 45056 | B70: 153.06662
A71: 45056.958 | C71: 45.640633 | D71: 8.7807693
A72: 45057 | B72: 153.32635
A73: 45057.958 | C73: 46.547878 | D73: 8.8064127
A74: 45058 | B74: 153.74594
A75: 45060.958 | C75: 46.667252 | D75: 8.9034891
A76: 45061 | B76: 154.86481
A77: 45061.958 | C77: 46.500126 | D77: 8.7981701
A78: 45062 | B78: 154.24542
A79: 45062.958 | C79: 46.659294 | D79: 8.8750982
A80: 45063 | B80: 155.80388
A81: 45063.958 | C81: 47.463078 | D81: 9.2264042
A82: 45064 | B82: 157.90176
A83: 45064.958 | C83: 47.630203 | D83: 9.2453098
A84: 45065 | B84: 159.26041
A85: 45067.958 | C85: 48.787964 | D85: 9.3256626
A86: 45068 | B86: 159.91975
A87: 45068.958 | C87: 48.592171 | D87: 9.4192505
A88: 45069 | B88: 163.2764
A89: 45069.958 | C89: 47.706818 | D89: 9.2037153
A90: 45070 | B90: 158.50116
A91: 45070.958 | C91: 47.825996 | D91: 9.1706295
A92: 45071 | B92: 156.82285
A93: 45071.958 | C93: 47.936672 | D93: 9.2093878
A94: 45072 | B94: 157.16252
A95: 45074.958 | C95: 47.757896 | D95: 9.1602297
A96: 45075.958 | C96: 47.068344 | D96: 9.1186361
A97: 45076 | B97: 155.64403
A98: 45076.958 | C98: 45.97868 | D98: 8.9579306
A99: 45077 | B99: 151.18851
A100: 45077.958 | C100: 46.370277 | D100: 9.0543537
...
